Workbook

Sheet BUSCA
Z1: SEGURADORAS_LISTA
B2: SISTEMA DE BUSCA DE SEGURADORAS | Z2: AIG Seguros
B3: Digite o nome da seguradora na célula amarela abaixo para visualizar seus dados | Z3: Akad Seguros
Z4: Alba- Aliança da Bahia
B5: Seguradora: | C5: AIG Seguros | D5: ← Digite ou selecione uma seguradora da lista | Z5: Alianz
Z6: Avla Seguradora
B7: ══════════════════════════════════════════════════════════════════════════════════════════ | Z7: Axa Seguros
B8: 📋 INFORMAÇÕES DA SEGURADORA SELECIONADA | Z8: Berkley Seguros
Z9: BMG Seguros
B10: 📁 PROPERTY (SLA) - Dados da Seguradora | Z10: Bradesco Seguros
Z11: Chubb Seguros
B12: Sistema | C12: =IF($C$5="","",IFERROR(VLOOKUP($C$5,'PROPERTY (SLA)'!$A:$Z,2,FALSE),"Não encontrado")) -> Não | Z12: Excelsor Seguros
B13: Trocar assunto do e-mail | C13: =IF($C$5="","",IFERROR(VLOOKUP($C$5,'PROPERTY (SLA)'!$A:$Z,3,FALSE),"Não encontrado")) -> Sem orientação a respeito Seguir padrão da Addvalora | Z13: FairFax Seguros
B14: Copiar analista nos e-mails | C14: =IF($C$5="","",IFERROR(VLOOKUP($C$5,'PROPERTY (SLA)'!$A:$Z,4,FALSE),"Não encontrado")) -> Sim | Z14: Fator
B15: SLA - 1º Contato e Agendamento | C15: =IF($C$5="","",IFERROR(VLOOKUP($C$5,'PROPERTY (SLA)'!$A:$Z,5,FALSE),"Não encontrado")) -> Orientação : Manter contato imediato após o recebimento do acionamento | Z15: FM Global
B16: SLA - Realização da Vistoria | C16: =IF($C$5="","",IFERROR(VLOOKUP($C$5,'PROPERTY (SLA)'!$A:$Z,6,FALSE),"Não encontrado")) -> Conforme agendamento / apresentar a sintese até 48h após a vistoria | Z16: Generali Seguros
B17: SLA - Relatório Preliminar | C17: =IF($C$5="","",IFERROR(VLOOKUP($C$5,'PROPERTY (SLA)'!$A:$Z,7,FALSE),"Não encontrado")) -> Até 5 dias após a vistoria | Z17: HDI Global
B18: SLA - Relatório Final | C18: =IF($C$5="","",IFERROR(VLOOKUP($C$5,'PROPERTY (SLA)'!$A:$Z,8,FALSE),"Não encontrado")) -> Até 7 dias após último documento | Z18: HDI Seguros
B19: Relatório modelo próprio | C19: =IF($C$5="","",IFERROR(VLOOKUP($C$5,'PROPERTY (SLA)'!$A:$Z,9,FALSE),"Não encontrado")) -> Não | Z19: Junto Seguros
B20: Períodos reiterações documentos | C20: =IF($C$5="","",IFERROR(VLOOKUP($C$5,'PROPERTY (SLA)'!$A:$Z,11,FALSE),"Não encontrado")) -> Sem orientação Sugestão: Reiterar a cada 10 dias | Z20: Liberty Seguros
B21: Prazo de encerramento | C21: =IF($C$5="","",IFERROR(VLOOKUP($C$5,'PROPERTY (SLA)'!$A:$Z,12,FALSE),"Não encontrado")) -> Sem informação / Sugestão: Confirmar com analista após 75 dias, se da continuidade ao processo | Z21: Mapfre
B22: Depreciação | C22: =IF($C$5="","",IFERROR(VLOOKUP($C$5,'PROPERTY (SLA)'!$A:$Z,13,FALSE),"Não encontrado")) -> Conforme apólice | Z22: Mitsui Seguros
B23: Salvados | C23: =IF($C$5="","",IFERROR(VLOOKUP($C$5,'PROPERTY (SLA)'!$A:$Z,15,FALSE),"Não encontrado")) -> Sem informação / E-mail para o analista | Z23: Newe
B24: Formulários Próprios | C24: =IF($C$5="","",IFERROR(VLOOKUP($C$5,'PROPERTY (SLA)'!$A:$Z,23,FALSE),"Não encontrado")) -> *Autorização de crédito *Declaração de outros seguros *Formulário de conformidade | Z24: Potencial Seguros
B25: Outros procedimentos | C25: =IF($C$5="","",IFERROR(VLOOKUP($C$5,'PROPERTY (SLA)'!$A:$Z,26,FALSE),"Não encontrado")) -> * Relatórios Preliminares 2,3,4....: A cada 30 dias, se houver informações que justifiquem, ou sempre que houver fatos relevantes, como alteração de Estimativas de indenização. Procedimentos e Honorários: Para valores de time sheet de até R$ 20.000,00, não há necessidade de aprovação prévia da AIG. | Z25: QBE Seguros
Z26: Sancor Seguros
Z27: Sombrero Seguros
B28: 📁 RCG (SLA) - Responsabilidade Civil Geral | Z28: Sompo Seguros
Z29: Sompo Seguros / TERCEIRIZAÇÃO ANÁLISE
B30: Sistema: | C30: =IF($C$5="","",IFERROR(VLOOKUP($C$5,'RCG (SLA)'!$A:$Z,2,FALSE),"Não disponível nesta categoria")) -> Não disponível nesta categoria | Z30: Sura Seguros
B31: Copiar analista: | C31: =IF($C$5="","",IFERROR(VLOOKUP($C$5,'RCG (SLA)'!$A:$Z,4,FALSE),"Não disponível nesta categoria")) -> Não disponível nesta categoria | Z31: Swiss Re
B32: SLA 1º Contato: | C32: =IF($C$5="","",IFERROR(VLOOKUP($C$5,'RCG (SLA)'!$A:$Z,5,FALSE),"Não disponível nesta categoria")) -> Não disponível nesta categoria | Z32: Tokio Marine
B33: SLA Relatório Final: | C33: =IF($C$5="","",IFERROR(VLOOKUP($C$5,'RCG (SLA)'!$A:$Z,8,FALSE),"Não disponível nesta categoria")) -> Não disponível nesta categoria | Z33: Zurich Seguros
B34: Prazo encerramento: | C34: =IF($C$5="","",IFERROR(VLOOKUP($C$5,'RCG (SLA)'!$A:$Z,12,FALSE),"Não disponível nesta categoria")) -> Não disponível nesta categoria
B35: Outros procedimentos: | C35: =IF($C$5="","",IFERROR(VLOOKUP($C$5,'RCG (SLA)'!$A:$Z,25,FALSE),"Não disponível nesta categoria")) -> Não disponível nesta categoria
B38: 📁 RCP (SLA) - Responsabilidade Civil Profissional
B40: Sistema: | C40: =IF($C$5="","",IFERROR(VLOOKUP($C$5,'RCP (SLA)'!$A:$Z,2,FALSE),"Não disponível nesta categoria")) -> Não disponível nesta categoria
B41: Copiar analista: | C41: =IF($C$5="","",IFERROR(VLOOKUP($C$5,'RCP (SLA)'!$A:$Z,4,FALSE),"Não disponível nesta categoria")) -> Não disponível nesta categoria
B42: SLA 1º Contato: | C42: =IF($C$5="","",IFERROR(VLOOKUP($C$5,'RCP (SLA)'!$A:$Z,5,FALSE),"Não disponível nesta categoria")) -> Não disponível nesta categoria
B43: SLA Relatório Final: | C43: =IF($C$5="","",IFERROR(VLOOKUP($C$5,'RCP (SLA)'!$A:$Z,8,FALSE),"Não disponível nesta categoria")) -> Não disponível nesta categoria
B44: Prazo encerramento: | C44: =IF($C$5="","",IFERROR(VLOOKUP($C$5,'RCP (SLA)'!$A:$Z,12,FALSE),"Não disponível nesta categoria")) -> Não disponível nesta categoria
B45: Outros procedimentos: | C45: =IF($C$5="","",IFERROR(VLOOKUP($C$5,'RCP (SLA)'!$A:$Z,25,FALSE),"Não disponível nesta categoria")) -> Não disponível nesta categoria
B48: 📁 GARANTIA JUDICIAL
B50: Sistema: | C50: =IF($C$5="","",IFERROR(VLOOKUP($C$5,'Garantia Judicial'!$A:$Z,2,FALSE),"Não disponível nesta categoria")) -> Não disponível nesta categoria
B51: Copiar analista: | C51: =IF($C$5="","",IFERROR(VLOOKUP($C$5,'Garantia Judicial'!$A:$Z,4,FALSE),"Não disponível nesta categoria")) -> Não disponível nesta categoria
B52: SLA 1º Contato: | C52: =IF($C$5="","",IFERROR(VLOOKUP($C$5,'Garantia Judicial'!$A:$Z,5,FALSE),"Não disponível nesta categoria")) -> Não disponível nesta categoria
B53: SLA Relatório Final: | C53: =IF($C$5="","",IFERROR(VLOOKUP($C$5,'Garantia Judicial'!$A:$Z,8,FALSE),"Não disponível nesta categoria")) -> Não disponível nesta categoria
B54: Prazo encerramento: | C54: =IF($C$5="","",IFERROR(VLOOKUP($C$5,'Garantia Judicial'!$A:$Z,12,FALSE),"Não disponível nesta categoria")) -> Não disponível nesta categoria
B55: Outros procedimentos: | C55: =IF($C$5="","",IFERROR(VLOOKUP($C$5,'Garantia Judicial'!$A:$Z,25,FALSE),"Não disponível nesta categoria")) -> Não disponível nesta categoria
B58: 📁 GARANTIA - RESSARCIMENTO
B60: Sistema: | C60: =IF($C$5="","",IFERROR(VLOOKUP($C$5,'Garantia - Ressarcimento'!$A:$Z,2,FALSE),"Não disponível nesta categoria")) -> Não disponível nesta categoria
B61: Copiar analista: | C61: =IF($C$5="","",IFERROR(VLOOKUP($C$5,'Garantia - Ressarcimento'!$A:$Z,4,FALSE),"Não disponível nesta categoria")) -> Não disponível nesta categoria
B62: SLA 1º Contato: | C62: =IF($C$5="","",IFERROR(VLOOKUP($C$5,'Garantia - Ressarcimento'!$A:$Z,5,FALSE),"Não disponível nesta categoria")) -> Não disponível nesta categoria
B63: SLA Relatório Final: | C63: =IF($C$5="","",IFERROR(VLOOKUP($C$5,'Garantia - Ressarcimento'!$A:$Z,8,FALSE),"Não disponível nesta categoria")) -> Não disponível nesta categoria
B64: Prazo encerramento: | C64: =IF($C$5="","",IFERROR(VLOOKUP($C$5,'Garantia - Ressarcimento'!$A:$Z,12,FALSE),"Não disponível nesta categoria")) -> Não disponível nesta categoria
B65: Outros procedimentos: | C65: =IF($C$5="","",IFERROR(VLOOKUP($C$5,'Garantia - Ressarcimento'!$A:$Z,25,FALSE),"Não disponível nesta categoria")) -> Não disponível nesta categoria
B68: 📁 GARANTIA - EXECUTANTE
B70: Sistema: | C70: =IF($C$5="","",IFERROR(VLOOKUP($C$5,'Garantia - Executante'!$A:$Z,2,FALSE),"Não disponível nesta categoria")) -> Não disponível nesta categoria
B71: Copiar analista: | C71: =IF($C$5="","",IFERROR(VLOOKUP($C$5,'Garantia - Executante'!$A:$Z,4,FALSE),"Não disponível nesta categoria")) -> Não disponível nesta categoria
B72: SLA 1º Contato: | C72: =IF($C$5="","",IFERROR(VLOOKUP($C$5,'Garantia - Executante'!$A:$Z,5,FALSE),"Não disponível nesta categoria")) -> Não disponível nesta categoria
B73: SLA Relatório Final: | C73: =IF($C$5="","",IFERROR(VLOOKUP($C$5,'Garantia - Executante'!$A:$Z,8,FALSE),"Não disponível nesta categoria")) -> Não disponível nesta categoria
B74: Prazo encerramento: | C74: =IF($C$5="","",IFERROR(VLOOKUP($C$5,'Garantia - Executante'!$A:$Z,12,FALSE),"Não disponível nesta categoria")) -> Não disponível nesta categoria
B75: Outros procedimentos: | C75: =IF($C$5="","",IFERROR(VLOOKUP($C$5,'Garantia - Executante'!$A:$Z,25,FALSE),"Não disponível nesta categoria")) -> Não disponível nesta categoria
B78: 📋 LISTA DE SEGURADORAS DISPONÍVEIS
B79: Selecione uma das seguradoras abaixo e digite o nome exato na célula amarela (C5):
B80: Coluna 1 | C80: Coluna 2 | D80: Coluna 3
B81: AIG Seguros | C81: FairFax Seguros | D81: Potencial Seguros
B82: Akad Seguros | C82: Fator | D82: QBE Seguros
B83: Alba- Aliança da Bahia | C83: FM Global | D83: Sancor Seguros
B84: Alianz | C84: Generali Seguros | D84: Sombrero Seguros
B85: Avla Seguradora | C85: HDI Global | D85: Sompo Seguros
B86: Axa Seguros | C86: HDI Seguros | D86: Sompo Seguros / TERCEIRIZAÇÃO ANÁLISE
B87: Berkley Seguros | C87: Junto Seguros | D87: Sura Seguros
B88: BMG Seguros | C88: Liberty Seguros | D88: Swiss Re
B89: Bradesco Seguros | C89: Mapfre | D89: Tokio Marine
B90: Chubb Seguros | C90: Mitsui Seguros | D90: Zurich Seguros
B91: Excelsor Seguros | C91: Newe
B93: 💡 Dica: Digite o nome exato da seguradora na célula amarela (C5) para buscar os dados

Sheet PROPERTY (SLA)
A1: Seguradora | B1: Sistema | C1: Trocar campo de assunto do e-mail | D1: Copiar o analista em todos os e-mails | E1: SLA - 1º Contato e agendamento vistoria | F1: SLA- Realização da vistoria / Síntese | G1: SLA - Relatório Preliminar | H1: SLA - Relatório Final | I1: Relatório de regulação modelo próprio | J1: Cronologia no relatório (sugestão utilizar em todos os processos) | K1: Períodos para reiterações de documentos (SLA) | L1: Prazo de encerramento sem manifestação / documentos- (Cycle Time) | M1: Depreciação | N1: Valor em Risco | O1: Salvados | Q1: Apresentação da apuração ao segurado antes da seguradora analisar os valores | R1: Emissão termo de acordo / demonstrativo de prejuízos | U1: Precisa enviar relatório final junto com time sheet / despesas | V1: Envio do relatório final junto com a nota fiscal | W1: Formulários Próprios | X1: Emissão carta de encerramento / Negativa | Z1: Outros procedimentos e assuntos
M2: Reter a D.V.N | O2: Área de Salvados | P2: Sistema | R2: Regulação | S2: Seguradora | T2: Modelo próprio | X2: Regulação | Y2: Seguradora
A3: AIG Seguros | B3: Não | C3: Sem orientação a respeito Seguir padrão da Addvalora | D3: Sim | E3: Orientação : Manter contato imediato após o recebimento do acionamento | F3: Conforme agendamento / apresentar a sintese até 48h após a vistoria | G3: Até 5 dias após a vistoria | H3: Até 7 dias após último documento | I3: Não | J3: Sim | K3: Sem orientação Sugestão: Reiterar a cada 10 dias | L3: Sem informação / Sugestão: Confirmar com analista após 75 dias, se da continuidade ao processo | M3: Conforme apólice | N3: E-mail para analista para ver se levanta o VR para prejuízos de até 5% do Valor em Risco Declarado ou atuar conforme particularidades da apólice Obs. Tem apólice que até determinado valor não apura o VR | O3: Sem informação / E-mail para o analista | P3: Sem informação | Q3: Sem orientação / ver com o analista | U3: Sem orientação a respeito | V3: Sem orientação a respeito | W3: *Autorização de crédito *Declaração de outros seguros *Formulário de conformidade | X3: Não | Y3: Sim | Z3: * Relatórios Preliminares 2,3,4....: A cada 30 dias, se houver informações que justifiquem, ou sempre que houver fatos relevantes, como alteração de Estimativas de indenização. Procedimentos e Honorários: Para valores de time sheet de até R$ 20.000,00, não há necessidade de aprovação prévia da AIG.
A4: Akad Seguros | B4: Sim | C4: Sem orientação a respeito Seguir padrão da Addvalora | D4: Não | E4: Orientação : Manter contato imediato após o recebimento do acionamento | F4: Conforme agendamento / apresentar a sintese até 48h após a vistoria | G4: Até 5 dias após a vistoria | H4: Até 5 dias após último documento | I4: Sim: Para prejuizos ate 300K / Prejuizos acima de 301K Modelo addvalora Property | J4: Sim | K4: A cada 05 dias | L4: 25 dias corridos (encerrar por falta de cobertura se sem documentos no 20º dia). | M4: Conforme apólice | N4: E-mail para analista para ver se levanta o VR para prejuízos de até 5% do Valor em Risco Declarado ou atuar conforme particularidades da apólice Obs. Tem apólice que até determinado valor não apura o VR | O4: Sem informação / E-mail para o analista | P4: Sem informação | Q4: Prejuizo ate 75K apresentar ao corretor/segurado sem análise prévia da Seguradora / Prejuizo acima de 75K somente após a analise e autorização da Seguradora | R4: Não | S4: Sim | T4: Sim | U4: Não | V4: Não | W4: Formulario PF / PJ | X4: Sim | Y4: Sim | Z4: *Consulta de prêmio no Digital para verificar se tem parcela pendente – se tiver pendência realizar a o cálculo de prazo curto (planilha em anexo); * Ao realizar espelhamento manter o analista em cópia para conhecimento da nova abertura. *Obrigatório Protocolo da Concessionária de Energia em caso de Danos Elétricos *Processo acima de 300 mil, fazer no relatório padrão Addvalora * Outros valores tem relatório simplificado * Pedidos de cadastros de dados bancários e cópia de apólices, devems ser direcionados à @Maria Souza, copiando as analistas @Isabella Silva e @Jemilli Silva. Não sendo necessário, manter as demais analistas em cópia. *Cobertura (telhado) de Postos de Combustiveis na AKAD é considerada como edificações abertas e ou semi-abertas e não tem amparo técnico na Garantia de Vendaval Utilizar os modelos de carta recusa da AKAD e enviar para validação prévia do analista. Obrigatório utilizar apenas os seguintes termos para encerramento: 1. Recusa Técnica: Sinistros sem cobertura. 2. Encerrado por falta de documentos: Sinistros encerrados por pendência documental. 3. Prejuízo abaixo da franquia: Quando o dano não atinge o valor da franquia. 4. Abertura indevida: Erro de apólice ou necessidade de troca de registro.
A5: Alba- Aliança da Bahia | B5: Sim | C5: Padrão nº da Seguradora e/ou Ticket / Nome do segurado / Nº Addvalora | D5: Para unidade UGC 2 - Seguradora criou e-mail Regulacao@alba.com.br (Para acionamentos e tratativas no decorrer do processo), copiar o analista também. | E5: Orientação : Manter contato imediato após o recebimento do acionamento/ mantendo todos os envolvidos em cópia. | F5: Conforme agendamento / apresentar a sintese até 24h após a vistoria ( dia util) | G5: Até 4 dias após a vistoria (confirmar SLA estipulada em contrato) | H5: Até 5 dias após último documento | I5: UGC 2 - Simplificado com logo Addvalora e ALBA | J5: Sim | K5: A cada 10 dias | L5: 90 dias | M5: Conforme apólice | N5: E-mail para analista para ver se levanta o VR para prejuízos de até 5% do Valor em Risco Declarado ou atuar conforme particularidades da apólice Obs. Tem apólice que até determinado valor não apura o VR | O5: Sem informação / E-mail para o analista | P5: Sem informação | Q5: Sempre enviar para validação da Seguradora, caso estejam de acordo , seguiremos com envio e apresentação ao segurado. | R5: Após a validação da Seguradora , submeteremos ao segurado o Demonstrativo e termo de acordo. | S5: não | T5: não | U5: Sem orientação a respeito | V5: Sem orientação a respeito | W5: Sem orientação a respeito | X5: Não | Y5: Sim | Z5: O login foi liberado, por enquanto, apenas para a usuária Katia Camillo (UGC2). Estamos auxiliando a seguradora no início do uso do sistema. Os procedimentos serão compartilhados com os demais quando o sistema estiver 100% funcional ou de acordo com a necessidade das equipes. A emissão das Notas Fiscais de Honorários deverá ser realizada de forma individualizada por processo de sinistro.
A6: Alianz | B6: Sim | C6: Sim /Seguir padrão da Addvalora | D6: Sem orientação a respeito | E6: Orientação : Manter contato imediato após o recebimento do acionamento | F6: Conforme agendamento / apresentar a sintese até 48h após a vistoria | G6: Até 7 dias após a vistoria | H6: Até 5 dias após último documento | I6: Não. Contudo, usamos um modelo simplificado | J6: Não. Vamos seguir a sugestão e inserir cronologia. | K6: Sugestão: Reiterar a cada 10 dias | L6: Sugestão: Confirmar com analista após 75 dias, se da continuidade ao processo | M6: Conforme apólice | N6: E-mail para analista para ver se levanta o VR para prejuízos de até 5% do Valor em Risco Declarado ou atuar conforme particularidades da apólice Obs. Tem apólice que até determinado valor não apura o VR | O6: E-mail para o analista | P6: Sim | Q6: Ver com o analista | R6: Não | S6: Sim | T6: Sim | U6: Não. Relatório Final inserido em Sistema. Time Sheet inserido em sistema. | V6: Não. Faturamento por lote | W6: Tabela Detalhada de Apuração de Prejuízos | X6: Sim | Y6: Não | Z6: *É muito importante que seja gerada uma nova versão de relatório preliminar toda vez que ocorra alguma atualização importante, tais como, alterações de estimativas e detalhes importantes quanto à cobertura. *O sistema deve ser utilizado para inserir tanto os Relatórios quanto a documentação relativa ao faturamento de honorários e despesas.Mesmo assim, deve ser enviado também aos cuidados do analista via e mail. Encaminhar e mail informando que o processo foi finalizado no sistema. *Na realização da 1ª Vistoria, devera ser entregue o formulário " Termo de Autorização de Pagamento de Sinistro mediante Crédito em Conta" a ser preenchido pelo Segurado. Essa solicitação deverá ser incluída em nossa "Relação de Documentos". *O Sistema deve ser alimentado após o retorno da vistoria e na conclusão da Regulação. * O sistema tem manual  Nomear os documentos que são indexados no sistema.  Atentar-se às solicitações dos analistas feitas através do painel de avisos do sistema.
A7: Avla Seguradora | B7: Não | C7: Seguir padrão da Addvalora | D7: Manter o e-mail "sinistrobr.property@avla.com" em todas tratativas | E7: Orientação : Manter contato imediato após o recebimento do acionamento | F7: Conforme agendamento / apresentar a sintese até 48h após a vistoria | G7: Até 5 dias após a vistoria | H7: Até 5 dias após último documento | I7: Não | J7: Sim | K7: Sugestão: Reiterar a cada 10 dias | L7: Sugestão: Confirmar com analista após 75 dias, se da continuidade ao processo | M7: Conforme apólice | N7: E-mail para analista para ver se levanta o VR para prejuízos de até 5% do Valor em Risco Declarado ou atuar conforme particularidades da apólice Obs. Tem apólice que até determinado valor não apura o VR | O7: E-mail para o analista | P7: Não | Q7: Ver com o analista | U7: Sem orientação a respeito | V7: Sem orientação a respeito | W7: Sem orientação a respeito | X7: Não | Y7: Sim
A8: Axa Seguros | B8: Sim | C8: Não/Inserir somente nº Addvalora | D8: Sim | E8: Orientação : Manter contato imediato após o recebimento do acionamento. | F8: Conforme agendamento / apresentar a sintese até 48h após a vistoria | G8: Até 2 dias após a vistoria | H8: Até 5 dias após último documento | I8: Sim. Utilizamos modelo simplificado | J8: Sim | K8: A cada 7 dias (UGC) | L8: 75 dias informar o analista que indicará o prazo adcional na reiteração. (UCG) | M8: Conforme apólice | N8: E-mail para analista para ver se levanta o VR para prejuízos de até 5% do Valor em Risco Declarado ou atuar conforme particularidades da apólice Obs. Tem apólice que até determinado valor não apura o VR | O8: Sim | P8: E-mail para área de Salvado e Analista (salvados.br@axa.com) | Q8: Não /Ver com o analista | R8: Não | S8: Sim | T8: Sim | U8: Sim. Inserir no sistema da seguradora | V8: Sim: anexadas no GIS em até 1 dia útil ao dia seguinte do envio do relatório final | W8: Formulário Guarda de Salvados | X8: Não | Y8: Sim | Z8: *Tem informações obrigatorias a ser inseridas nos relatórios (vide Baruc) *Modelo padrão da Seguradora para Relatorio Preliminares, Finais, Ata de Vistoria e Relatório Fotografico. Para os ramos (Riscos Nomeados/ Riscos Operacionais/ Riscos de Engenharia), será mantido o modelo da Addvalora. *A indicação da região para deslocamento, quando do aviso de sinistro, poderá ser negociada com a Cia., desde que seja apresentada justificativa plausível (Ex. robustez necessária / regulador com mais expertise devido ao tipo de sinistro / cliente especial / etc); *E-mail: salvados.br@axa.com , copiando sempre o analista do processo. * Para carteira do Posto Ipiranga ver as condições e prazos diferenciados; * Criar tarefa para o analista no sistema ao inserir os relatórios * Continuar enviando os relatórios também por e-mail ao analista * Tem manual do sistema As NFs de Honorários devem ser enviadas e anexadas no GIS em até 1 dia útil ao dia seguinte do envio do relatório final
A9: Berkley Seguros | B9: Não | C9: Seguir padrão da Addvalora | D9: Sem orientação a respeito | E9: Orientação : Manter contato imediato após o recebimento do acionamento | F9: Conforme agendamento / apresentar a sintese até 48h após a vistoria | G9: Até 7 dias após a vistoria | H9: Até 7 dias após último documento | I9: Não | J9: Sim | K9: Sem orientação Sugestão: Reiterar a cada 10 dias | L9: Sem informação / Sugestão: Confirmar com analista após 75 dias, se da continuidade ao processo | M9: Conforme apólice | N9: E-mail para analista para ver se levanta o VR para prejuízos de até 5% do Valor em Risco Declarado ou atuar conforme particularidades da apólice Obs. Tem apólice que até determinado valor não apura o VR | O9: Sem informação / E-mail para o analista | P9: Sem informação | Q9: Sem orientação / ver com o analista | U9: Sem orientação a respeito | V9: Sem orientação a respeito | W9: Sem orientação a respeito | X9: Não | Y9: Sim | Z9: *Relatórios Preliminares 2,3 4, .... : A cada 30 dias, se houver informações que justifiquem, ou sempre que houver fatos relevantes, como alteração de Estimativa de Indenização
A10: BMG Seguros | B10: Não | C10: Não/Inserir somente nº Addvalora | D10: Sim | E10: Orientação : Manter contato imediato após o recebimento do acionamento | F10: Conforme agendamento / apresentar a sintese até 48h após a vistoria | G10: Até 5 dias após a vistoria | H10: Até 5 dias após último documento | I10: Não | J10: Sim | K10: A cada 15 dias | L10: 90 dias | M10: Conforme apólice | N10: E-mail para analista para ver se levanta o VR para prejuízos de até 5% do Valor em Risco Declarado ou atuar conforme particularidades da apólice Obs. Tem apólice que até determinado valor não apura o VR | O10: Sem informação / E-mail para o analista | P10: Sem informação | Q10: Não /Ver com o analista | R10: Sim | S10: Não | T10: Não | U10: Não | V10: Não | W10: *Autorização de crédito *Formulário de conformidade | X10: Sim | Y10: Sim | Z10: *É muito importante que seja gerada uma nova versão de relatório preliminar toda vez que ocorra alguma atualização importante, tais como, alterações de estimativas e detalhes importantes quanto à cobertura. *Tanto os Relatórios quanto a documentação relativa ao faturamento de honorários e despesas.Mesmo assim, deve ser enviado também aos cuidados do analista via e mail. * Reiteração de documentos a cada 15 dias
A11: Bradesco Seguros | B11: Sim | C11: Sem orientação a respeito Seguir padrão da Addvalora | D11: Sem orientação a respeito | E11: Orientação : Manter contato imediato após o recebimento do acionamento | F11: Conforme agendamento / apresentar a sintese até 48h após a vistoria | G11: Até 5 dias após a vistoria | H11: Até 5 dias após último documento | I11: Não | J11: Sim | K11: Sem orientação Sugestão: Reiterar a cada 10 dias | L11: Sem informação / Sugestão: Confirmar com analista após 75 dias, se da continuidade ao processo | M11: Conforme apólice | N11: E-mail para analista para ver se levanta o VR para prejuízos de até 5% do Valor em Risco Declarado ou atuar conforme particularidades da apólice Obs. Tem apólice que até determinado valor não apura o VR | O11: Sem informação / E-mail para o analista | P11: Sem informação | Q11: Sem orientação / ver com o analista | R11: Sim | S11: Não | T11: Sim | U11: Sem orientação a respeito | V11: Sem orientação a respeito | W11: *Autorização para crédito em conta *Termo de guarda de salvados | X11: Não | Y11: Sim | Z11: *A Bradesco também aplica depreciação sobre Mão-de-Obra. *na apuração dos prejuízos e no cálculo da indenização para a cobertura de Roubo, que prevê limitação por unidade sinistrada e proporcionalização das franquias. Para este cálculo, devemos utilizar um quadro disponibilizado pela Bradesco. * Para os sinistros de Danos Elétricos, concluídos a partir do dia 15/04/2019, dos ramos: Residencial, Condomínio e Empresarial, que tenham ocorrido nas cidades (localizadas no Nordeste) elencadas na 2ª aba desta planilha. Assim, as Reguladoras de Sinistros devem orientar os Corretores e/ou Segurados, durante a regulação, que os bens sinistrados, reconhecidamente amparados pelo seguro e que por ventura não compense a sua recuperação (Perda total), deverão ser preservados, conforme previsto nas condições do seguro, para que no final do processo (após a indenização) sejam recolhidos por uma empresa contratada da Bradesco Auto/RE para a destinação adequada. Após a indenização, a empresa recicladora contratada fará o contato com o Segurado visando agendar a data de recolhimento dos salvados, seja no local do sinistro ou na assistência técnica. As Reguladoras de Sinistros deverão informar detalhadamente no Relatório de Regulação a descrição dos salvados de forma completa (quantidade, descrição, marca, modelo e n.º de série) e incluir fotografia (se possível). *Antes de "enviar para análise" no SARE, o Relatório Final e o Time Sheet devem ser submetidos a prévia análise do analista da Cia. Seguradora para aprovação. *Novos procedimentos: 1) Imediatamente após receber pedidos de reaberturas com envio de documentos que estavam pendentes, seja enviado pelo segurado ou pelo corretor, a reguladora deverá comunicar por e-mail ao respectivo supervisor do pro 2) A reguladora deverá responder ao segurado e/ou corretor que os documentos A, B e C foram recebidos e serão analisados por um prazo máximo de 5 dias corridos para que eles tenham uma posição se os documentos são suficientes para reabertura do processo ou não; 2.1) Caso negativo, o segurado e/ou corretor serão informados quais documentos ainda permanecem pendentes e esta mensagem também deverá ser incluída pelo supervisor no SARE. 2.2) Caso positivo, a reguladora deverá solicitar a reabertura do processo no SARE para o respectivo Supervisor para inclusão de Adendo RRS, bem como informar o valor da reserva a ser constituída. Mesmo com processo encerrado no SARE, como tudo estará registrado pelo supervisor, a Central terá acesso ao movimento dos processos.
A12: Chubb Seguros | B12: Sim | C12: Não/Inserir somente nº Addvalora | D12: Sim. Os relatórios devem ser enviados para sinistro.sme@chubb.com, copiando o analista | E12: Orientação : Manter contato imediato após o recebimento do acionamento | F12: Conforme agendamento / apresentar a sintese até 48h após a vistoria | G12: Até 5 dias após a vistoria | H12: Até 5 dias após último documento | I12: Não | J12: Sim | K12: A cada 15 dias | L12: 30 dias (Regulação) + 30 dias (Liquidação). | M12: Conforme apólice | N12: E-mail para analista para ver se levanta o VR para prejuízos de até 5% do Valor em Risco Declarado ou atuar conforme particularidades da apólice Obs. Tem apólice que até determinado valor não apura o VR | O12: Sim | P12: Não / Enviar e-mail para salvados-singrandesriscos@Chubb.com com cópia ao analista do sinistro. | Q12: 1-Em caso de Property não apresentar. 2- Para processo SME não apresentar. | R12: Sim | S12: Não | T12: Sim | U12: Não | V12: Não | W12: *Formulário de Salvados *Autorização de crédito *Formulário de conformidade | X12: Sim | Y12: Sim | Z12: *Para envio de Relatórios ao analista, deve copiar o e-mail sinistro.sme@chubb.com *No corpo do e-mail, deve estar explícita a informação sobre o tipo de relatório enviado à Chubb acompanhado dos seguintes itens adicionais: * Nomear relatórios conforma padrão da seguradora, conforme exemplos: 01_RegulacaoPreliminar_“Ordem de Pagamento SIS , 02_RegulacaoFinal_“Ordem de Pagamento SIS *No corpo do e-mail, deve estar explícita a informação sobre o tipo de relatório enviado à Chubb acompanhado dos seguintes itens adicionais: -Tipo de Relatório -Data de Entrega do último documento fornecido pelo segurado/corretor -Discriminação (Boletim de Ocorrência, por exemplo) -SLA *Nos casos de SME fica mantido o procedimento de envio do demonstrativo de apuração dos prejuízos ao segurado e corretor. Ressaltando que em todos os casos deve ser observado o texto a seguir para evitarmos transtornos junto ao cliente: “Declaro ainda, estar ciente de que o presente termo não implica, por parte da Seguradora, na obrigação do pagamento da indenização pelo sinistro reclamado, a qual fica sujeita às Condições Contratuais, eventuais limitações (tal como o Limite Máximo de Indenização) e eventuais deduções (tais como a franquia, salvados, depreciação e rateio), que regem o contrato de seguro.” O demonstrativo e termo de ciência dos valores não deve ser contabilizado como data de último documento, desta forma, não é obrigatório assinatura do segurado com a concordância de valores. Toda a comunicação com a analista Marina Dantas deve seguir critérios específicos: Não copiar em e-mails de rotina, como solicitações e reiterações de documentos ou envio de ata para assinatura. Copiar quando for necessária sua intervenção, parecer ou esclarecimento técnico. Copiar no envio dos seguintes documentos: ata já assinada, relatório fotográfico, relatório preliminar, relatório final e notas fiscais. Nesses casos, manter também em cópia o e-mail sinistro.sme@chubb.com Envio obrigatório de relatório semanal todas as segundas-feiras com o estágio atualizado de cada sinistro em andamento. O prazo de regulação/liquidação suspende-se por no máximo 2 (duas) vezes para solicitação de documentos. Relatórios finais devem conter: coberturas afetadas, limites, memória de cálculo detalhada (franquias, juros, atualização) e fundamentação fática/legal em caso de recusa.
A13: Excelsor Seguros | B13: Não | C13: Sim /Seguir padrão da Addvalora | D13: Sim / Também a caixa departamental (sinistros@excelsior.com.br) | E13: Orientação : Manter contato imediato após o recebimento do acionamento | F13: Conforme agendamento / apresentar a sintese até 48h após a vistoria | G13: Até 7 dias após a vistoria | H13: Até 7 dias após último documento | I13: Não | J13: Sim | K13: Sem orientação Sugestão: Reiterar a cada 10 dias | L13: Sem informação / Sugestão: Confirmar com analista após 75 dias, se da continuidade ao processo | M13: Conforme apólice | N13: E-mail para analista para ver se levanta o VR para prejuízos de até 5% do Valor em Risco Declarado ou atuar conforme particularidades da apólice Obs. Tem apólice que até determinado valor não apura o VR | O13: E-mail para o analista | P13: Sem informação | Q13: Solicitar aprovação ao analista | R13: Não | S13: Sim | T13: Não | U13: Não | V13: Não | W13: Carta de Posicionamento (Minuta enviada para o analista) | X13: Não | Y13: Sim | Z13: *Relatórios Preliminares 2, 3, 4....... : A cada 30 dias, se houver informações que justifiquem, ou sempre que houver fatos relevantes, como ateração de Estimativas de Indenização *Caixa departamental: sinistros@excelsiorseguros.com.br
A14: FairFax Seguros | B14: Não | C14: Não /Inserir somente nº Addvalora no final | D14: Copiar a caixa departamental (sin-property@fairfax.com.br) | E14: Orientação : Manter contato imediato após o recebimento do acionamento | F14: Conforme agendamento / apresentar a sintese até 48h após a vistoria | G14: Até 7 dias após a vistoria | H14: Até 7 dias após último documento | I14: Não | J14: Sim | K14: Sugestão: Reiterar a cada 10 dias | L14: 90 dias informar ao analista e solicitar prazo para encerramento (costumam dar mais 30 dias) | M14: Conforme apólice | N14: E-mail para analista para ver se levanta o VR para prejuízos de até 5% do Valor em Risco Declarado ou atuar conforme particularidades da apólice Obs. Tem apólice que até determinado valor não apura o VR | O14: E-mail para o analista + corporativo | P14: E-mail | Q14: Solicitar aprovação ao analista | R14: Demonstrativo de prejuízos | S14: Termo de quitação | T14: Não | U14: Não. Encaminhar e-mail para aprovação do TS | V14: Não. Nota Fiscal segue aprós aprovação do TS | W14: Autorização para Crédito em conta | X14: Não | Y14: Sim | Z14: * Não será necessário o envio de e-mail de agradecimento * Para os sinistros em que haja o envio de relatório preliminar, final ou adendo. Sugerimos, incluir nas primeiras linhas do e- mail um recorte/print do Cálculo de reserva, que constará no relatório em anexo, isso facilitará a identificação de casos de maiores perdas, logo ao receber o e-mail. *O assunto dos e-mails enviados para a Fairfax não pode ser alterado para o padrão da Addvalora, podemos apenas inserir a referência da Addvalora, pois tem restrições de caracteres no referido campo. *A Seguradora possui e mail corporativo: sin-property@fairfax.com.br. *Todas as tratativas com à Seguradora devem ser feitas pelo e mail corporativo, NUNCA devemos enviar os e mails diretamente para o Analista., salvo na UGR, conforme orientação do Clark, sempre copiam, além da caixa departamental, o analista do processo e na maioria das vezes, o José Eduardo e o José Luiz (por solicitação dos próprios). *Quando enviar e-mail diretamente para o Segurado (agendamento da vistoria ou outros por orientação do Corretor) deve-se colocar o sin-property em cópia normal.
A15: Fator | B15: Não | C15: Padrão nº da Seguradora e/ou Ticket / Nome do segurado / Nº Addvalora | D15: Sim / Incluir obrigatoriamente a chave: docsin@fatorseguradora.com.br | E15: Orientação : Manter contato imediato após o recebimento do acionamento/ mantendo todos os envolvidos em cópia. | F15: Conforme agendamento / apresentar a sintese até 24h após a vistoria ( dia util) | G15: Até 3 dias após a vistoria | H15: Até 7 dias após último documento | I15: Modelo Addvalora (Property) | J15: Sim | K15: A cada 15 dias | L15: Referido prazo de 90 dias, com a anuência expressa da Seguradora, deverá ser elaborada correspondência, informando o encerramento do sinistro no prazo de 10 (dez) dias. | M15: Conforme apólice | N15: E-mail para analista para ver se levanta o VR para prejuízos de até 5% do Valor em Risco Declarado ou atuar conforme particularidades da apólice Obs. Tem apólice que até determinado valor não apura o VR | O15: Sem informação / E-mail para o analista | P15: Não há | Q15: Sempre enviar para validação da Seguradora, caso estejam de acordo , seguiremos com envio e apresentação ao segurado. | R15: Sim | S15: sim | T15: sim | U15: sim | V15: Tabela pode enviar o RF + NF dos honorários. | W15: Papel timbrado | X15: Sim | Y15: Não | Z15: *Caixa departamental - sinistros@fatorseguradora.com.br; *Todos os sinistros que envolvam valores de prejuízos relevantes, deverão ser discutidos previamente com o analista responsável pelo processo na Fator antes da emissão do relatório intermediário/preliminar. 1. Informar imediatamente o recebimento do último documento. 2. Enviar planilha de controle (Anexo 1) até o 5º dia útil do mês. 3. Follow-up judicial a cada 60 dias. 4. Resposta ao segurado: sempre "Em Análise". Sempre que houver o recebimento do último documento necessário à análise do sinistro, deverá ser enviado e-mail ao analista responsável da Seguradora, informando que a documentação necessária foi integralmente apresentada, bem como a data de recebimento do último documento. Da mesma forma, caso sejam identificadas, após a vistoria e/ou contato preliminar com o Segurado ou seu Representante, dúvidas ou indícios quanto ao enquadramento do evento nas coberturas contratadas, a Fator deverá ser comunicada com a maior brevidade possível.
A16: FM Global | B16: Não | C16: Sem orientação a respeito Seguir padrão da Addvalora | D16: Sim | E16: Orientação : Manter contato imediato após o recebimento do acionamento | F16: Conforme agendamento / apresentar a sintese até 48h após a vistoria | G16: Até 5 dias após a vistoria | H16: Até 5 dias após último documento | I16: Não | J16: Sim | K16: Sem orientação Sugestão: Reiterar a cada 10 dias | L16: Sem informação / Sugestão: Confirmar com analista após 75 dias, se da continuidade ao processo | M16: Conforme apólice | N16: E-mail para analista para ver se levanta o VR para prejuízos de até 5% do Valor em Risco Declarado ou atuar conforme particularidades da apólice Obs. Tem apólice que até determinado valor não apura o VR | O16: Sem informação / E-mail para o analista | P16: Sem informação | Q16: Sem orientação / ver com o analista | U16: Sem orientação a respeito | V16: Sem orientação a respeito | W16: Sem orientação a respeito | X16: Não | Y16: Sim
A17: Generali Seguros | B17: Sim | C17: Não / Seguir padrão orientado pela seguradora | D17: Sim | E17: Orientação : Manter contato imediato após o recebimento do acionamento | F17: Conforme agendamento / apresentar a sintese até 24h após a vistoria | G17: Até 48 horas da realização da vistoria | H17: Até 5 dias após último documento | I17: Não | J17: Sim | K17: A cada 15 dias | L17: 90 dias | M17: Conforme apólice | N17: E-mail para analista para ver se levanta o VR para prejuízos de até 5% do Valor em Risco Declarado ou atuar conforme particularidades da apólice Obs. Tem apólice que até determinado valor não apura o VR | O17: E-mail para o analista / inserção no sistema | P17: Sem informação | Q17: Sim | R17: Sim | S17: sim | T17: Não | U17: Apresentar junto ao relatório final a estimativa do TS | V17: Não | W17: Não | X17: Não | Y17: Sim | Z17: Padrão de assunto de e-mail - E mails enviados para a Generali devem seguir o seguinte padrão: Agendamento Vistoria: Sinistro xxxxxx - Segurado: < Nome do Segurado> - Apólice: xxxxxx - Aviso: xxxxxxx Relatório Preliminar: Relatório Preliminar - Sinistro: xxxxx - Segurado: < Nome do Segurado> / Relatório Final: Relatório Final - Sinistro: xxxxx - Segurado: < Nome do Segurado > * No caso do Relatório Final, os arquivos devem ser enviados na seguinte ordem: NF honorarios e recibo despesas, Relatório de Regulação, e por último os anexos. Honorários e Despesas de Regulação: A partir de 13 de setembro de 2024, é obrigatório incluir nos relatórios preliminares, finais e loss advices os valores estimados de honorários e despesas de regulação de forma separada. Esta medida visa aprimorar o controle das reservas financeiras.
A18: HDI Global | B18: Sim | C18: Seguir padrão da Seguradora e acrescentar n° Addvalora | D18: Sim | E18: Orientação : Manter contato imediato após o recebimento do acionamento | F18: Conforme agendamento / apresentar a sintese até 48h após a vistoria | G18: Até 5 dias após a vistoria | H18: Até 5 dias após a vistoria | I18: Não | J18: Sim | K18: Semanalmente | L18: Compeltado 75 dias encaminhar ultima cobrnça com prazo de 15 para finalização ADM. | M18: Conforme apólice | N18: E-mail para analista para ver se levanta o VR para prejuízos de até 5% do Valor em Risco Declarado ou atuar conforme particularidades da apólice Obs. Tem apólice que até determinado valor não apura o VR | O18: Sem informação / E-mail para o analista | P18: Sem informação | Q18: Com anuência da seguradora | R18: Sim | S18: Sim | T18: Não | U18: Sim | V18: Sim | W18: Autorização para Crédito em conta | X18: Não | Y18: Sim | Z18: *Se receber documentos tem até 48 horas para responder o corretor sobre pendências * Caso seja necessário o envio de relatório traduzido, este deverá ser encaminhado em até 7 dias da solicitação da HDI Global. *Caso seja necessário o envio de adendo aos relatórios, este deverá ser encaminhado em até 05 dias da solicitação da HDI Global. * Inserir nº Call Center e nº Hans nos Relatórios * Para o preenchimento do sistema, ver manual *Inserir o número da reiteração de documentos a cada envio de e-mail ao segurado /corretor Ao finalizar o processo: 1) Quando da finalização do processo, verificar se a pessoa que assinará a TED tem poderes e se a documentação encaminhada atende os requisitos. 2) Em caso de procuração, favor se atentar para a validade do documento; 3) Em alguns casos, há necessidade de assinatura de 02 ou mais representantes da Empresa, portanto, a documentação encaminhada deverá atender estes requisitos; 4) Quando do encerramento do processo pelo tempo decorrido, o regulador deverá mencionar todas as datas de reiterações e os documentos ainda pendentes Modelo de Relatório: Devem ser enviados no modelo "Draft" (com marca d’água) para validação prévia do analista. Conteúdo: Não devem conter opiniões sobre enquadramento de coberturas. Texto Obrigatório: Incluir ao final de cada relatório o texto padrão de isenção de responsabilidade da seguradora. Relatórios Traduzidos: Prazo de envio em até 2 dias da solicitação. Confirmação de Documentos: Prazo de 48 horas para confirmar recebimento e apontar pendências ao corretor/segurado. Reforma Tributária (2026): Notas fiscais a partir de 01/01/2026 devem destacar IBS/CBS (alíquota teste 1%) conforme nova cláusula 1.4 do contrato. Plantão de Emergência: Em recessos (como final de ano), utilizar os contatos específicos das áreas (Corporate: Diogo/Edmilson/Jorge/Thais; Massificados: Klauss/Toninho/Eliomar; Grandes Riscos: Luciano). Solicitação de Documentos (não é necessário solicitar): Formulário Cadatral dos Beneficiários, RG/CPF do Segurado, RG/CPF do Beneficiário, Cópia do Cartão CNPJ, Contrato Social, RG/CPF dos Sócios da Empresa. Solicitar contrato social somente se for necessário comprovação de vínculo se o comprovante de endereço não estiver nominal ao segurado. Não copiar os Analistas em todas as trocas de e-mails: Apenas naqueles em que for preciso um retorno dele; Envio da DRL: Utilizar o sistema da HDI, inclusive, para as reiterações; Reiterações: frequência semanal; Quadro Demonstrativo de Apuração: Indexar no sistema apenas após o “de acordo” do Corretor/Segurado; Quadro Demonstrativo de Apuração: Alçada de R$ 50k para envio sem prévia avaliação do Analista da Cia; Solicitação de Documentos: enviada após a validação do Analista da Cia ao Informe Preliminar. Documentação SUSEP: Não há necessidade (exceção: Para os sinistros de Danos Elétricos há necessidade do envio do comprovante de endereço (conta de luz emitida pela concessionária de energia)). Não utilizar o seguinte texto: Documentos necessários para a regulação solicitados ao Corretor nesta data. Orientação ao RCG: a regulação de sinistros envolvendo automóveis está sendo realizada pela própria Seguradora. Portanto, orienta-se questionar a companhia assim que o acionamento for recebido, registrando essa informação imediatamente no sistema. Sempre que a regulação exigir mais de 40 horas dedicadas, o colaborador deve obrigatoriamente acionar o contato na Área de Sinistros da Seguradora.
A19: HDI Seguros | B19: Sim | C19: Seguir padrão da Addvalora | D19: sim | E19: Orientação : Manter contato imediato após o recebimento do acionamento e atualizar o sistema da seguradora com a data da vistoria | F19: Conforme agendamento / apresentar a sintese até 48h após a vistoria | G19: Até 48 horas após a vistoria | H19: Até 5 dias após último documento | I19: Não | J19: Sim | K19: Semanalmente | L19: Sugestão: Confirmar com analista após 75 dias, se da continuidade ao processo | M19: Conforme apólice | N19: E-mail para analista para ver se levanta o VR para prejuízos de até 5% do Valor em Risco Declarado ou atuar conforme particularidades da apólice Obs. Tem apólice que até determinado valor não apura o VR | O19: Sim | P19: E-mail para analista | Q19: Não /Ver com o analista | R19: Sim / mas após aval do analista | S19: Sim | T19: Não | U19: Inserimos no sistema após envio do final | V19: Não | W19: Não | X19: Não | Y19: Sim | Z19: * Tem procedimentos para preenchimento da agenda no sistema ( manual no Baruc) *Tem regra para aplicação de franquia (LMI) e salvados * Tem que constar na ata ou preliminar se ter algum tipo de seguro inclusive habitacional quando for o caso. Modelo de Relatório: Devem ser enviados no modelo "Draft" (com marca d’água) para validação prévia do analista. Conteúdo: Não devem conter opiniões sobre enquadramento de coberturas. Texto Obrigatório: Incluir ao final de cada relatório o texto padrão de isenção de responsabilidade da seguradora. Relatórios Traduzidos: Prazo de envio em até 2 dias da solicitação. Confirmação de Documentos: Prazo de 48 horas para confirmar recebimento e apontar pendências ao corretor/segurado. Reforma Tributária (2026): Notas fiscais a partir de 01/01/2026 devem destacar IBS/CBS (alíquota teste 1%) conforme nova cláusula 1.4 do contrato. Plantão de Emergência: Em recessos (como final de ano), utilizar os contatos específicos das áreas (Corporate: Diogo/Edmilson/Jorge/Thais; Massificados: Klauss/Toninho/Eliomar; Grandes Riscos: Luciano). Solicitação de Documentos (não é necessário solicitar): Formulário Cadatral dos Beneficiários, RG/CPF do Segurado, RG/CPF do Beneficiário, Cópia do Cartão CNPJ, Contrato Social, RG/CPF dos Sócios da Empresa. Solicitar contrato social somente se for necessário comprovação de vínculo se o comprovante de endereço não estiver nominal ao segurado. Não copiar os Analistas em todas as trocas de e-mails: Apenas naqueles em que for preciso um retorno dele; Envio da DRL: Utilizar o sistema da HDI, inclusive, para as reiterações; Reiterações: frequência semanal; Quadro Demonstrativo de Apuração: Indexar no sistema apenas após o “de acordo” do Corretor/Segurado; Quadro Demonstrativo de Apuração: Alçada de R$ 50k para envio sem prévia avaliação do Analista da Cia; Solicitação de Documentos: enviada após a validação do Analista da Cia ao Informe Preliminar. Documentação SUSEP: Não há necessidade (exceção: Para os sinistros de Danos Elétricos há necessidade do envio do comprovante de endereço (conta de luz emitida pela concessionária de energia)). Não utilizar o seguinte texto: Documentos necessários para a regulação solicitados ao Corretor nesta data. Orientação ao RCG: a regulação de sinistros envolvendo automóveis está sendo realizada pela própria Seguradora. Portanto, orienta-se questionar a companhia assim que o acionamento for recebido, registrando essa informação imediatamente no sistema.
A20: Junto Seguros | B20: Não | C20: Sem orientação a respeito Seguir padrão da Addvalora | D20: Não | E20: Orientação : Manter contato imediato após o recebimento do acionamento | F20: Conforme agendamento / apresentar a sintese até 24h após a vistoria | G20: Até 5 dias após a vistoria | H20: Até 5 dias após último documento | I20: Não | J20: Sim | K20: Sem orientação Sugestão: Reiterar a cada 10 dias | L20: Sem informação / Sugestão: Confirmar com analista após 75 dias, se da continuidade ao processo | M20: Conforme apólice | N20: E-mail para analista para ver se levanta o VR para prejuízos de até 5% do Valor em Risco Declarado ou atuar conforme particularidades da apólice Obs. Tem apólice que até determinado valor não apura o VR | O20: Sem informação / E-mail para o analista | P20: Sem informação | Q20: Sem orientação /Ver com o analista | U20: Sem orientação a respeito | V20: Sem orientação a respeito | W20: Sem orientação a respeito | X20: Não | Y20: Sim
A21: Liberty Seguros | B21: Sim | C21: Sim /Seguir padrão da Addvalora | D21: Sim | E21: Orientação : Manter contato imediato após o recebimento do acionamento | F21: Conforme agendamento / apresentar a sintese até 48h após a vistoria | G21: Até 7 dias após a vistoria | H21: Até 7 dias após último documento | I21: Não | J21: Sim | K21: Sugestão: Reiterar a cada 10 dias | L21: Sugestão: Confirmar com analista após 75 dias, se da continuidade ao processo | M21: Conforme apólice | N21: E-mail para analista para ver se levanta o VR para prejuízos de até 5% do Valor em Risco Declarado ou atuar conforme particularidades da apólice Obs. Tem apólice que até determinado valor não apura o VR | O21: E-mail para o analista | P21: Sem informação | Q21: Não /Ver com o analista | R21: Não | S21: Sim | T21: Não | U21: Sem orientação a respeito | V21: Sem orientação a respeito | W21: Sem orientação a respeito | X21: Não | Y21: Sim | Z21: *Relatórios Finais com apuração de indenização deveram vir acompanhados pelo Formulário Padrão da Liberty, Formulário Susep 445 " cadastro de beneficiário" *Fornece informações até o 2º dia útil de cada semana " informações sobre o desenvolvimento de Trabalhos de Regulação". *Relatórios Preliminares 2,3,4....: A cada 30 dias, se houver informações que justifiquem, ou sempre que houver fatos relevantes, como alteração de Estimativas de Idenização. * Link de acesso ao Portal Yelum (Liberty): https://www.portaldesegurosyelum.com.br/Inicio/login_prestadores.aspx
A22: Mapfre | B22: Sim | C22: Sem orientação a respeito Seguir padrão da Addvalora | D22: Sim | E22: Orientação : Manter contato imediato após o recebimento do acionamento | F22: Conforme agendamento / apresentar a sintese até 24h após a vistoria | G22: Até 3 dias após a vistoria | H22: Até 5 dias após último documento | I22: Não | J22: Sim | K22: A cada 15 dias | L22: Passados 90 dias da solicitação inicial dos documentos , consultar a seguradora | M22: Conforme apólice | N22: E-mail para analista para ver se levanta o VR para prejuízos de até 5% do Valor em Risco Declarado ou atuar conforme particularidades da apólice Obs. Tem apólice que até determinado valor não apura o VR | O22: Sim | P22: E-mail para analista | Q22: Não /ver com o analista | R22: Sim / mas após aval do analista | T22: Sim | U22: Sem orientação a respeito | V22: Sem orientação a respeito | W22: Formulário PPE - Pessoa Jurídica e Física / Formulário de Autorização de crédito / Formulário de Identificação dos sócios / Formulário de declaração de Inexistência de outros seguros Demonstrativo de prejuízos / Recibo Quitação | X22: Não | Y22: Sim | Z22: *A Mapfre possui um sistema informatizado semelhante ao nosso, que deve ser alimentado após o retorno da vistoria e quando da conclusão da regulação. É importante o devido registro no sistema deles, já que em caso de inconformidade, o analista não consegue constituir reserva e efetuar o pagamento da indenização e dos honorários. No sistema da Seguradora, devemos preencher apenas as abas denominadas: parecer, valores e documentos. * Inserir o relatório do Firstone somente após a avaliação do analista
A23: Mitsui Seguros | B23: Não | C23: Seguir padrão da Addvalora | D23: Em todas tratativas manter: documentosinistro@msig.com.br | E23: Orientação : Manter contato imediato após o recebimento do acionamento | F23: Conforme agendamento / apresentar a sintese até 48h após a vistoria | G23: Até 5 dias após a vistoria - Prejuizos até R$ 100mil Até 10 dias Prejuízos acima de R$ 100mil | H23: Até 5 dias após último documento - prejuizo até R$ 100mil Até 10 dias após último documento - prejuizo acima de R$ 100mil | I23: Não | J23: Sim | K23: A cada 15 dias e ao completar 75 dias, conceder prazo de +15dias | L23: 75 dias | M23: Conforme apólice | N23: E-mail para analista para ver se levanta o VR para prejuízos de até 5% do Valor em Risco Declarado ou atuar conforme particularidades da apólice Obs. Tem apólice que até determinado valor não apura o VR | O23: E-mail para o analista | P23: Email | Q23: Sim - Até R$ 200 mil - com ressalva a que seguradora fará análise dos valores . Não - Acima de R$ 200 mil | R23: Sim - Até R$ 200mil | S23: Sim | T23: Sim | U23: Sim | V23: Sim. Não colocar a palavra Kit no anexo de honorários e despesas | W23: Termo de Quitação de Sinistro | X23: Não | Y23: Sim | Z23: *Responder e-mails em até 48 horas; *Colocar Relatório, síntese e fotográfico em único arquivo pdf; *Temos liberdade para sugestão de adiantamento mesmo sem solicitação o segurado; * Negativa pode ser adiantada ao corretor antes de submeter a seguradora; *Preliminares II, III, encaminhar e-mail somente ao analista; * Termo de Acordo: incluir texto que os valores serão submetidos para avaliação da Seguradora * Caso receba acionamento que ultrapasse 200km, solicitar aprovação para o analista antes de seguir com o atendimento; *Relatórios Preliminares e Intermediários, o assunto do e-mail deve seguir – Aviso: N° Sinistro (123456) – Sinistro 0118000000 – Segurado ABCD *Relatório Final e Adendo, o assunto do e-mail deve seguir – AVISO 123456 DT_ULTIMO _DOC – DD/MM/AAAA A equipe da Mitsui deve ser copiada em todas as comunicações com o corretor/segurado através do e-mail documentosinistro@msig.com.br. Notas fiscais e despesas devem acompanhar o Relatório Final. Não se deve usar a palavra "Kit" na descrição de honorários e despesas. Ajuste de Reserva: Sempre que houver um ajuste de reserva, é necessário elaborar um relatório preliminar e contatar o analista. Variações de até 20% podem dispensar o relatório, dependendo do valor do prejuízo, mas o contato com o analista é essencial. Peritos: A condução do perito é responsabilidade do regulador, que deve indicar o tipo de perícia necessária. A seguradora cobre os custos de apenas um regulador de campo e um perito por vistoria. Adiantamentos: Os reguladores têm autonomia para sugerir adiantamentos, mesmo sem solicitação, comunicando previamente o analista. Atenção especial para adiantamentos acima de R$ 500.000,00. Termo de Acordo: Para processos de até R$ 200.000,00, o termo deve incluir um texto informando que os valores serão validados pela seguradora. Acima desse valor, o processo deve ser submetido à aprovação prévia da seguradora antes do envio do termo.
A24: Newe | B24: Não | C24: Sem orientação a respeito Seguir padrão da Addvalora | D24: Sem orientação a respeito | E24: Orientação : Manter contato imediato após o recebimento do acionamento | F24: Conforme agendamento / apresentar a sintese até 48h após a vistoria | G24: Até 5 dias úteis nos casos sem perícia e até 10 dias úteis nos casos com perícia. | H24: Até 3 dias úteis após último documento | I24: Não | J24: Sim | K24: Solicitação de documentos: até 24 horas úteis; Análise de documentos: até 7 dias úteis nos casos sem perícia e até 10 dias úteis nos casos com perícia; | L24: 30 dias - NLS | M24: Conforme apólice | U24: Não | V24: Não | Z24: A rotina de faturamento fica padronizada da seguinte forma: Emissão de 1 NF e 1 recibo por mês; Envio das informações para validação até o dia 05 do mês subsequente, no modelo disponibilizado pela Newe; Individualização dos valores por número de sinistro e apólice; Envio com prefixo obrigatório [FATURAMENTO] para os e-mails juridico@neweseguros.com e produtos.juridico@neweseguros.com; Validação pela Newe até o dia 10; e Emissão da NF + recibo com vencimento no dia 20.
A25: Potencial Seguros | B25: Sim | C25: Sem orientação a respeito Seguir padrão da Addvalora | D25: Sem orientação a respeito | E25: Orientação : Manter contato imediato após o recebimento do acionamento | F25: Conforme agendamento / apresentar a sintese até 48h após a vistoria | G25: Até 5 dias após a vistoria | H25: Até 5 dias após último documento | I25: Sim / Tem modelo apenas para exemplos de tópicos a serem utilizados | J25: Sim | K25: Sem orientação Sugestão: Reiterar a cada 10 dias | L25: Sem informação / Sugestão: Confirmar com analista após 75 dias, se da continuidade ao processo | M25: Conforme apólice | N25: E-mail para analista para ver se levanta o VR para prejuízos de até 5% do Valor em Risco Declarado ou atuar conforme particularidades da apólice Obs. Tem apólice que até determinado valor não apura o VR | O25: Sem informação / E-mail para o analista | P25: Sem informação | Q25: Sem orientação /Ver com o analista | U25: Sem orientação a respeito | V25: Sem orientação a respeito | W25: Sem orientação a respeito | X25: Não | Y25: Sim | Z25: *Contato para agendamento de vistoria, indicação de prejuízo em até 48 horas *Emissão de Relatório Final até 05 dias corridos após a entrega do último documento *Tem modelo de planilha de apuração no Baruc RD Valor Atual: Para obtenção do valor atual de equipamentos, o regulador de sinistro deverá além de solicitar as cotações ao segurado, obter também suas próprias cotações no mercado, junto à revendedores de equipamentos iguais ou similares ao sinistrado; - Caso as cotações apresentas pelo segurado estiver de acordo com os valores praticados pelo mercado, considerar esses valores como valor atual - Caso houver discrepância entre as cotações apresentadas pelo segurado, deveremos adotar ou as cotações obtidas pelo regulador de sinistro ou lançar mão de métodos de depreciação constante das condições gerais da apólice (Ross-Heideck) *Sinistro sem Cobertura Técnica: Se por ocasião da pre-análise ou durante a vistoria do regulador de sinistro, em ficando constatado que o evento não possui cobertura técnica na apólice do segurado, o regulador não deverá emitir no momento opinião a respeito da cobertura ou não do sinistro. Contudo, deverá ser solicitado ao segurado somente a documentação mínima necessária para comprovação do sinistro (negativa) e os prejuízos. *Seguradora solicita que a reguladora agilize os processos de sinistros para os casos em que estiver evidente a exclusão da cobertura técnica, não passar ao Segurado “Termo de Acordo de Prejuízos”. Passar apenas um documento denominado “demonstrativo de valores apurados”, sem necessitar pegar o de acordo do segurado e também não solicitar documentos de SUSEP, dados bancários, etc... A documentação para sinistros cuja cobertura estiver flagrantemente excluída, a regulação deverá ser agilizada, não criar expectativa de indenização ao segurado e limitar a solicitar documentos necessários a comprovação de causa, danos e prejuízos. *Não deixar de inserir no corpo do Relatório de Regulação de Sinistros (relatório modelo Pottencial já passado em reunião realizada na Pottencial recentemente), fotografias do equipamento sinistrado, modelo novo, numeração da gravação de chassi legível (não se limitar a plaqueta de identificação do equipamento), se possível número de motor também. Essa numeração deve estar devidamente compatível com a apólice do segurado. Tiveram casos para liquidar que não tinha a fotografia legível da gravação do chassi, apenas a foto da placa de identificação da máquina. Isso pode deixar a Cia. Seguradora vulnerável em alguma situação. * Se atentar para sinistros envolvendo Cortees e Soldas. Texto no Baruc * Nos relatórios, seguir como padrão o capitulo 02 como sendo onde descrevemos o SEGURADO.
A26: QBE Seguros | B26: Não | C26: Sem orientação a respeito Seguir padrão da Addvalora | D26: Sem orientação a respeito | E26: Orientação : Manter contato imediato após o recebimento do acionamento | F26: Conforme agendamento / apresentar a sintese até 48h após a vistoria | G26: Até 5 dias após a vistoria | H26: Sem orientação a respeito/ Considerar até 5 dias após último documento | I26: Não | J26: Sim | K26: Sem orientação Sugestão: Reiterar a cada 10 dias | L26: Sem informação / Sugestão: Confirmar com analista após 75 dias, se da continuidade ao processo | M26: Conforme apólice | N26: E-mail para analista para ver se levanta o VR para prejuízos de até 5% do Valor em Risco Declarado ou atuar conforme particularidades da apólice Obs. Tem apólice que até determinado valor não apura o VR | O26: Sem informação / E-mail para o analista | P26: Sem informação | Q26: Sem orientação /Ver com o analista | R26: Sem orientação a respeito | S26: Sem orientação a respeito | T26: Sem orientação a respeito | U26: Sem orientação a respeito | V26: Sem orientação a respeito | W26: Sem orientação a respeito | X26: Não | Y26: Sim
A27: Sancor Seguros | B27: Sim | C27: Sim/ Seguir padrão da Addvalora | D27: Copiar a Caixa departamental | E27: Orientação : Manter contato imediato após o recebimento do acionamento | F27: Conforme agendamento / apresentar a sintese até 48h após a vistoria | G27: Até 48 horas da realização da vistoria | H27: Até 5 dias após último documento | I27: Não | J27: Sim | K27: A cada 10 dias | L27: 90 dias | M27: Conforme apólice | N27: E-mail para analista para ver se levanta o VR para prejuízos de até 5% do Valor em Risco Declarado ou atuar conforme particularidades da apólice Obs. Tem apólice que até determinado valor não apura o VR | O27: Sem informação / E-mail para o analista | P27: Sem informação | Q27: Sem orientação /Ver com o analista | R27: Sim/ Mas com o aval da da seguradora | U27: Sem orientação a respeito | V27: Sem orientação a respeito | W27: Sem orientação a respeito | X27: Não | Y27: Sim | Z27: Todos os pedidos de aprovação de timesheet devem ser encaminhados ao analista responsável, com o endereço sinistrosdespesas@fatorseguradora.com.br em cópia. *Se não recebermos documentos no prazo de 15/20 dias, podemos apurar e apresentar ao corretor/segurado, para ver se concordamos com os valores, dependendo do caso e tipo de dano. *Sempre que houver a possibilidade de apurar (casos de negativas) sem a solicitação de documentos, devemos fazer a apuração no relatório preliminar ou final, por causa das incidências de casos judiciais. *Em casos como de vendaval (destelhamento), caso o segurado não encaminhe documentos, podemos apurar (com a ajuda dos nossos especialistas) e submeter ao segurado caso ele concorde com os valores, podemos fechar o processo. *Em processos que não há dúvidas ou problemas, podemos encaminhar o Termo de Valores ao corretor/segurado, sem anuência da segurança, porém sempre deixando informado no Termo de Acordo, que os valores serão submetidos para a análise da Seguradora. Caso identifique algum problema, casos que fogem da curva, submeta o Relatório antes de ligar para segurança validar (copiar caixa departamental). *Se não recebermos documentos no prazo de 15/20 dias, podemos apurar e apresentar ao corretor/segurado, para ver se concordamos com os valores, dependendo do caso e tipo de dano.
A28: Sombrero Seguros | B28: Não | C28: Sem orientação a respeito Seguir padrão da Addvalora | D28: Sem orientação a respeito | E28: Orientação : Manter contato imediato após o recebimento do acionamento/ mantendo todos os envolvidos em cópia. | F28: Conforme agendamento / apresentar a sintese até 24h após a vistoria ( dia util) | G28: Até 5 dias após a vistoria | H28: Até 5 dias após último documento | I28: Modelo Addvalora (Property) | J28: Sim | K28: Sem orientação Sugestão: Reiterar a cada 10 dias | L28: Sem informação / Sugestão: Confirmar com analista após 75 dias, se da continuidade ao processo | M28: Conforme apólice | N28: E-mail para analista para ver se levanta o VR para prejuízos de até 5% do Valor em Risco Declarado ou atuar conforme particularidades da apólice Obs. Tem apólice que até determinado valor não apura o VR | O28: Sem informação / E-mail para o analista | P28: E-mail para analista | Q28: Sempre enviar para validação da Seguradora, caso estejam de acordo , seguiremos com envio e apresentação ao segurado. | R28: Sim/ Mas com o aval da da seguradora | S28: sim | T28: sim | U28: Sem orientação a respeito | V28: Tabela pode enviar o RF + NF dos honorários. | W28: Sem orientação a respeito | X28: Não | Y28: Sim
A29: Sompo Seguros | B29: NÃO | C29: Padrão da Seguradora- É obrigatório identificar o tipo de relatório no assunto. Ex. Preliminar : Relatório Preliminar - Segurado Sompo: XXXX - Sinistro Sompo: xxxxxxx - Apólice Sompo: xxxxx Final: Relatório de Regulação Final - Segurado Sompo: XXXX - Sinistro Sompo: xxxxxxx - Apólice Sompo: xxxxx | D29: Sim /docsinistrore@sompo.com.br / relatorios.sinistrocorporativo@sompo.com.br | E29: Orientação : Máximo de 2 horas úteis para contato (segurado/corretor). Máximo de 12 horas para responder por e-mail com os dados de agendamento. | F29: Realização da Vistoria: Em até 24 horas da data do acionamento. Síntese/Ata: Em até 24h úteis após a vistoria. | G29: Laudo Preliminar Final: Máximo de 48 horas após a realização da vistoria. Relatórios Parciais/Finais: Até 4 dias úteis (com perícia) ou 6 dias úteis (sem perícia) após recebimento dos documentos. | H29: Relatórios Parciais e Finais: Até 4 dias úteis (com participação de perícia) ou 6 dias úteis (sem participação de perícia) após o recebimento dos documentos. | I29: UGC 2 - Simplificado até R$ 50 Mil com logo Addvalora e Sompo . Acima de R$ 50mil (modelo Property Addvalora) | J29: Sim | K29: A cada 7 dias / encerrar casos (Até 100K) por falta de documentos que já tenham passado de 90 dias sem apresentação de documentos - conceder + 15 dias para encerramento | L29: Ramo 118 - 90 dias Ramo 351 - 140 dias Grandes Riscos -160 dias | M29: Somente acima de R$ 25.000.00 | N29: E-mail para analista para ver se levanta o VR para prejuízos de até 5% do Valor em Risco Declarado ou atuar conforme particularidades da apólice Obs. Tem apólice que até determinado valor não apura o VR | O29: Sim | P29: E-mail para analista | Q29: Sempre enviar para validação da Seguradora, caso estejam de acordo , eles enviarão para o de acordo do segurado | R29: Sim/ Mas com o aval da da seguradora | S29: sim | T29: sim | U29: Sem orientação a respeito | V29: Tabela pode enviar o RF + NF dos honorários. | W29: *Modelo de demonstrativo de prejuízos *Circular Susep ( FIC ) | X29: Não | Y29: Sim | Z29: *Copiar a caixa departamental docsinistrore@sompo.com.br em todas as tratativas com o segurado/corretor. *Toda vez que a vistoria não for realizada em até 48 horas a partir do recebimento da vistoria, os esclarecimentos dos motivos pelos quais houve a demora deverá ser informado no preliminar de vistoria impreterivelmente no primeiro paragrafo. Outras informações encontram-se na aba "Instruções Regulação". Solicitamos uma atenção especial nos prazos (atrasos), pois o Contrato prevê multa (redução dos honorários).Essa regra não se aplica ao Garantia. *Reforçamos que em todos os casos em que o endereço do local do sinistro for divergente do endereço do local de risco assegurado pela apólice, a primeira coisa que a reguladora tem que fazer é identificar se o endereço do local de risco é existente em algum outro lugar, pois caso exista, o evento se encontrará desprovido de cobertura técnica, a menos que haja comunicação interna entre os 2 endereços. *Em casos de Danos Elétricos, solicitar ao segurado para providenciar o protocolo junto a concessionária de energia elétrica. Envio de documentos: Devem ser nomeados e enviados em formato ZIP, copiando o e-mail docsinistrore@sompo.com.br. Envio de relatórios (preliminar e final): Enviar ao analista e copiar os e-mails docsinistrore@sompo.com.br e relatorios.sinistrocorporativo@sompo.com.br. Danos Elétricos: Em casos de danos elétricos, é obrigatório solicitar o Laudo Técnico assinado para fins de possível ressarcimento. Critérios de Análise e Indenização: Diferença de Valor de Novo (DVN): Pagamentos de DVN de até R$ 25.000,00 podem ser realizados sem a necessidade de envio das notas fiscais de reposição. O regulador pode, no entanto, solicitar as notas se julgar necessário, justificando o motivo. Cotações de Prédio: Fontes como PINI e SINAPI servem apenas como parâmetro. A fixação do prejuízo não deve se basear nelas, mas sim em orçamentos de empresas que de fato realizarão o serviço. Deve-se negociar com o orçamentista do segurado ou solicitar novos orçamentos se os valores estiverem muito acima da média. Cotações de Conteúdo: O objetivo é avaliar se o valor pleiteado está de acordo com a média de mercado, e não apenas encontrar o item mais barato. Deve-se ter bom senso, considerando variações aceitáveis, como a diferença de preços entre lojas físicas e online. O frete deve ser cotado e incluído no cálculo, sem aplicação de depreciação. Riscos de Engenharia (Roubo/Furto Qualificado): É preciso atenção a um sublimite para roubo/furto de materiais a incorporar à obra, que pode estar descrito no final da apólice, com franquia específica. Créditos Tributários: a seguradora disponibiliza um texto padrão para a solicitação de informações sobre créditos tributários (ICMS, IPI, etc.), que deve ser usado nas comunicações com o segurado * Outras particularidades específicas podem ser consultadas no link: https://drive.google.com/drive/folders/1WvdFQ46w9W5behyLYzs7wKcn7-jQ3mat?usp=drive_link Envio da DRL: Máximo de 24 horas após a vistoria (encaminhar ao corretor, copiando analista e docsinistrore@sompo.com.br). Relação de Sinistros Pendentes: Envio Semanal (às sextas-feiras) para relatoriosregrandesriscos@sompo.com.br. Solicitação de Docs. Complementares (> R$ 800 mil): Obrigatório alinhamento prévio e aprovação do analista responsável antes de qualquer solicitação de novos documentos não iniciais. (Vigência: 01/12/2025) SLA Sompo Retorno (Aprovação Doc. Complementar): Até 48 horas úteis (após e-mail do prestador). (Vigência: 01/12/2025)
A30: Sompo Seguros / TERCEIRIZAÇÃO ANÁLISE | B30: Sim / Apenas UGC 2 | C30: Padrão nº da Seguradora e/ou Ticket / Nome do segurado / Nº Addvalora | D30: Sim / docsinistrore@sompo.com.br E | E30: Para garantir o cumprimento do SLA, o processo deve ser atualizado no SAP em até 2 horas. A tratativa inicial, realizada pelas Analistas, deve incluir obrigatoriamente: Lançamento das reservas iniciais, mesmo que em valores mínimos. Estimativa de prejuízos /Honorários de regulação/ Despesas ou custos de análise. | F30: Conforme agendamento / apresentar a sintese até 24h após a vistoria ( dia util) | G30: Até 5 dias após a vistoria | H30: Até 5 dias após último documento | I30: UGC 2 - Simplificado até R$ 50 Mil com logo Addvalora e SOmpo / de R$ 50.000,01 até R$ 100 K (modelo Property Addvalora) | J30: Sim | K30: A cada 7 dias / encerrar casos (Até 100K) por falta de documentos que já tenham passado de 90 dias sem apresentação de documentos - conceder + 15 dias para encerramento | L30: Sem informação / Sugestão: Confirmar com analista após 75 dias, se da continuidade ao processo | M30: Somente acima de R$ 25.000.00 | N30: E-mail para analista para ver se levanta o VR para prejuízos de até 5% do Valor em Risco Declarado ou atuar conforme particularidades da apólice Obs. Tem apólice que até determinado valor não apura o VR | O30: Sim | P30: E-mail para analista | Q30: Analista terceirizada enviará para o Segurado apuração para o "de acordo" bem como a solicitação do FIC. | R30: Sim/ Mas com o aval da da seguradora | S30: sim | T30: sim | U30: Sem orientação a respeito | V30: Tabela pode enviar o RF + NF dos honorários. | W30: *Modelo de demonstrativo de prejuízos *Circular Susep ( FIC ) | X30: não | Y30: Sim | Z30: Analistas terceirizadas, sempre enviar apolice para equipe regulação / atualizações em Sistema / analise de todo material de regulação / realizações de pagamentos de indenização , honorários e despesas com processo / emissão dee cartas / análises de contestações de negativas
A31: Sura Seguros | B31: Sim | C31: Sim /Seguir padrão da Addvalora | D31: Sim | E31: Orientação : Manter contato imediato após o recebimento do acionamento | F31: Conforme agendamento / apresentar a sintese até 48h após a vistoria | G31: Até 5 dias após a vistoria | H31: Até 5 dias após último documento | I31: Não | J31: Sim | K31: Sem orientação Sugestão: Reiterar a cada 10 dias | L31: Sem informação / Sugestão: Confirmar com analista após 75 dias, se da continuidade ao processo | M31: Conforme apólice | N31: E-mail para analista para ver se levanta o VR para prejuízos de até 5% do Valor em Risco Declarado ou atuar conforme particularidades da apólice Obs. Tem apólice que até determinado valor não apura o VR | O31: Sem informação / E-mail para o analista | P31: Sem informação | Q31: Sem orientação /Ver com o analista | U31: Sem orientação a respeito | V31: Sem orientação a respeito | W31: *Carta de encerramento *Termo de acordo *Formulárioa Susep 612/20 | X31: Não | Y31: Sim | Z31: *Fornecer a Seguradora até o 2º dia útil de cada semana "Informação sobre desenvolvimento dos Trabalhos de Regulação". *Tem manual do sistema no Baruc
A32: Swiss Re | B32: Sim | C32: Seguir padrão da Addvalora | D32: Sim / Também a caixa departamental (BRDoc_Corporatesolutions@swissre.com) | E32: Orientação : Manter contato imediato após o recebimento do acionamento | F32: Conforme agendamento / apresentar a sintese até 48h após a vistoria | G32: 3 dias após vistoria (Standard) ou 5 dias (Complex). | H32: 5 dias após último documento (Standard) ou 10 dias (Complex). | I32: Sim. Utilizamos modelo simplificado | J32: Sim | K32: A cada 7 dias (Standard) ou 10 dias (Complex). | L32: Sugestão: Confirmar com analista após 75 dias, se da continuidade ao processo | M32: Conforme apólice | N32: E-mail para analista para ver se levanta o VR para prejuízos de até 5% do Valor em Risco Declarado ou atuar conforme particularidades da apólice Obs. Tem apólice que até determinado valor não apura o VR | O32: E-mail para o analista | P32: Sem informação | Q32: Não /Ver com o analista | R32: Não | S32: Sim | T32: Não | U32: Sim | V32: Sim | W32: Não | X32: Não | Y32: Sim | Z32: 1. Limite de 2 solicitações de docs complementares (sinistros > 500 SM); 2. Prazo legal de 30 dias para análise de cobertura (Art. 68); 3. Solicitação de docs em lote (DRL); 4. Uso de canal dedicado para gestão de documentos.
A33: Tokio Marine | B33: Sim | C33: Sem orientação a respeito Seguir padrão da Addvalora | D33: Não | E33: Conforme SLA Sistema | F33: Conforme agendamento / apresentar a sintese até 48h após a vistoria | G33: Até 48 horas após a vistoria | H33: Até 5 dias após último documento | I33: Não, porém há um modelo simplificado aprovado pela seguradora para o Ramo 18 | J33: Sim | K33: A cada 7 dias / Conforme sistema | L33: 125 dias empresarial 290 dias Emg. / RNO | M33: Somente acima de R$ 15.000,00 | N33: E-mail para analista para ver se levanta o VR para prejuízos de até 5% do Valor em Risco Declarado ou atuar conforme particularidades da apólice Obs. Tem apólice que até determinado valor não apura o VR | O33: Sim | P33: Sim | Q33: Sim /Com ressalva a que seguradora fará análise dos valores . | R33: Sim | S33: Não | T33: Sim | U33: Sem orientação a respeito | V33: Sem orientação a respeito | W33: *Formulário Guarda de Salvados * Declaração de Ciência de Valores (Timbrado) *Termo de Compromisso de Devolução de Bens * Reclamação de prejuízos à concessionária de energia elétrica (protocolo) * Formulário Autorização para crédito de indenização de sinistro | X33: Não | Y33: Sim | Z33: *Formulário Guarda de Salvados * Declaração de Ciência de Valores (Timbrado) *Termo de Compromisso de Devolução de Bens * Reclamação de prejuízos à concessionária de energia elétrica (protocolo) * Formulário Autorização para crédito de indenização de sinistro * Formulário de para danos elétricos Para os sinistros em que houver aplicação de depreciação, com retenção de valor a título de DVN (diferença de valor de novo), o RELATÓRIO DE REGULAÇÃO DE SINISTRO deve ser indexado no sistema da Cia. Seguradora como RELATÓRIO INTERINO, mesmo ele sendo o Relatório Final. Isso porque o processo continuará aberto com a Reguladora e a Seguradora, aguardando o prazo estipulado na apólice para indenização do valor da DVN. Caso seja um sinistro de grande complexidade em que o volume de informações não seja suportado pelo sistema, temos que desenvolver um relatório em “Word” com o mesmo layout ao constante no portal do regulador e fazer o upload dele (PDF) no portal da Tokio. (*) Somente o Relatório Final. Os Relatórios Preliminares e Intermediários devem ser elaborados no modelo da Addvalora Brasil. (Informação confirmada com o Sr. Alessandro Pasti (08.07.2019)). Temos a sugestão de elaborar o Relatório Final, também, no modelo padrão Addvalora, tendo em vista que o modelo da Tokio é suscinto e poderão ocorrer questionamentos por parte da Cia. Seguradora. *Responder e-mail dentro de 24horas *Em caso de dúvida tem manual do Portal para consulta no Baruc
A34: Zurich Seguros | B34: Sim | C34: Não /Inserir somente nº Addvalora no final | D34: Sim | E34: Orientação : Manter contato imediato após o recebimento do acionamento | F34: Conforme agendamento / apresentar a sintese até 48h após a vistoria | G34: Até 5 dias após a vistoria | H34: Até 10 dias após último documento | I34: Não | J34: Sim | K34: A cada 15 dias e ao completar 75 dias, comnceder prazo de +15dias (regra para sinistros de até R$ 1 milhão) | L34: Ao compeltar 75 dias encaminhar ver com analista prazo para encerramento | M34: Conforme apólice | N34: Apura para qualquer valor e não vale a sugestão de 5% do prejuízo X VRD (Para os processos que realizamos UGC, não foi necessário levantamento do VRD) | O34: Sim | P34: E-mail para analista | Q34: Não /Ver com o analista | R34: Não | S34: Sim | T34: Sim | U34: Sim | V34: Inserir a nota fiscal no sistema | W34: *Modelo de Aviso de Sinistro *Declaração de outros seguros | X34: Não | Y34: Sim | Z34: *Formulário Aviso de sinistro / declaração de outros seguros *Ao estabelecer reserva para sinistros, deve-se considerar: - Todos os fatos pertinentes do sinistro e estabelecer uma reserva para indenização que reflita a atual avaliação de exposição ( prejuízo) - Estimativa realista das despesas que provavelmente serão incorridas com a gestão e liquidação do sinistro. *Indicadores de Fraude - pedimos que a informação em relação ao quadro encaminhado, seja num arquivo apartado aos relatórios, tendo em vista que por muitas vezes os corretores e segurados recebem os documentos e trata-se de informação sensível *Para Fast Track tem orientações no Baruc para agilidade nos processos, desde o primeiro contato até a elaboração do relatório final ( simplificado) *Projeto Facility - processo abaixo da 100K ( regulação simples e sem burocracia) - Confirmar se está rodando este projeto

Sheet RCG (SLA)
A1: Seguradora | B1: Sistema | C1: Trocar campo de assunto do e-mail | D1: Copiar o analista em todos os e-mails | E1: SLA - 1º Contato e agendamento vistoria | F1: SLA- Realização da vistoria / Síntese | G1: SLA - Relatório Preliminar | H1: SLA - Relatório Final | I1: Relatório de regulação modelo próprio | J1: Cronologia no relatório (sugestão utilizar em todos os processos) | K1: Períodos para reiterações de documentos (SLA) | L1: Prazo de encerramento sem manifestação / documentos- (Cycle Time) | M1: Valor em Risco | N1: Salvados | P1: Apresentação da apuração ao segurado antes da seguradora analisar os valores | Q1: Emissão termo de acordo / demonstrativo de prejuízos | T1: Precisa enviar relatório final junto com time sheet / despesas | U1: Envio do relatório final junto com a nota fiscal | V1: Formulários Próprios | W1: Emissão carta de encerramento / Negativa | Y1: Outros procedimentos e assuntos
A2: AXA – ADM | B2: GIS (Financial Lines e Property) – https://sinistro.axa.com.br/Portal/Base/Login/LoginPortal.aspx | C2: N/A | D2: Sim — copiar o analista responsável e pagamentoprestador.br@axa.com nos envios de faturamento. | E2: Contato com segurado/corretor: 24h; agendamento da vistoria/reunião: 24h. | F2: N/A | G2: 5 dias úteis após vistoria ou acionamento (em casos sem vistoria). | H2: 5 dias úteis após o recebimento do último documento. | I2: N/A — utiliza modelo padrão Addvalora. | J2: N/A | K2: 10 dias corridos. | L2: 30 dias (sem retorno/reiterações ou pendência documental) — sob consulta ao analista. | M2: Conforme apólice / prejuízo apurado. Não há limite expresso. | N2: N/A | O2: N/A | P2: Sim — “Kit Faturamento” inclui demonstrativo de prejuízos (enviar ao analista). | Q2: Sim — processos por hora: enviar timesheet para aprovação antes do faturamento. | R2: Sim — enviar relatório final + kit com a NF e cópia para pagamentoprestador.br@axa.com. | S2: N/A | T2: N/A | U2: - Abertura imediata; prazo regular 90 dias. Honorários por tabela e hora (R$170/h). Despesas: R$1,30/km; alimentação R$30; hospedagem 3★. | V2: Não | W2: Padrão | X2: Padrão
A3: CHUBB – ADM | B3: Portal Chubb (vendorassignment.chubb.com) | C3: N/A | D3: Sim — sempre copiar o analista; relatórios e cobranças para sinistro.sme@chubb.com. | E3: N/A | F3: N/A | G3: N/A | H3: N/A | I3: N/A | J3: N/A | K3: N/A | L3: N/A | M3: Conforme apólice / prejuízo apurado. | N3: Enviar formulário/aviso de salvados para salvados-singrandesriscos@chubb.com com cópia ao analista. | O3: N/A | P3: N/A | Q3: Sim — enviar RF + NF + timesheet/recibos/comprovantes juntos para sinistro.sme@chubb.com. | R3: Sim — caixa departamental sinistro.sme@chubb.com (copiar analista). | S3: N/A | T3: Carta negativa enviada pelo analista da Chubb ao corretor; regulador não deve antecipar entendimento. | U3: Padronizar nomes dos anexos (ACSEL/SIS). Não encerrar processo sem anuência do analista. Alimentação R$44; deslocamento R$1,52/km; hospedagem 3★. | V3: Não | W3: Padrão | X3: Padrão
A4: FAIRFAX – ADM | B4: Acesso somente para a Katia por enquanto | C4: Campo de assunto não pode ser alterado; apenas inserir referência Addvalora. | D4: Sim — sempre copiar o analista e o e-mail corporativo sin-rc@fairfax.com.br. | E4: N/A | F4: N/A | G4: N/A | H4: N/A | I4: N/A | J4: N/A | K4: N/A | L4: N/A | M4: Conforme apólice / prejuízo apurado. | N4: N/A | O4: N/A | P4: N/A | Q4: N/A | R4: N/A | S4: N/A | T4: N/A | U4: Instrução de e-mails: copiar sin-rc@fairfax.com.br e o analista; não alterar assunto padrão.
A5: GENERALI – Judicial | B5: GIS BRASIL | C5: N/A | D5: N/A | E5: 24h contato; 24h abertura. | F5: N/A | G5: 7 dias (Relatório Preliminar). | H5: 7 dias (Relatório Final). | I5: N/A | J5: N/A | K5: Não se aplica (reiter.) | L5: 365 dias (Prazo de Regulação – Judicial e RC Empregador). | M5: Conforme apólice / prejuízo apurado. | N5: N/A | O5: N/A | P5: N/A | Q5: Processo por hora conforme TS; quando aplicável. | R5: N/A | S5: N/A | T5: N/A | U5: Indexar no GIS; posicionamento por carta; franquia/RC Obras conforme POP.
A6: NGB – ADM | B6: Opera com fluxos via e-mail e diretrizes internas | C6: N/A | D6: N/A | E6: Imediato contato; 24h vistoria (quando aplicável). | F6: N/A | G6: N/A | H6: N/A | I6: N/A | J6: N/A | K6: N/A | L6: Até 365 dias (regulação) — quando aplicável. | M6: Conforme apólice / prejuízo apurado. | N6: N/A | O6: N/A | P6: N/A | Q6: Timesheet quando processo por hora; faturamento conforme POP. | R6: N/A | S6: N/A | T6: Diretrizes de portal/atualização vinculadas a procedimentos Tokio; salvados, DRL e encerramento definidos por POP.
A7: TOKIO MARINE – ADM | B7: Portal do Prestador | C7: N/A | D7: N/A | E7: Imediato contato; agendamento 24h. | F7: N/A (síntese/ata junto ao RP) | G7: Relatório Preliminar: conforme POP; prorrogação permitida 1x (mediante ciência do coordenador). | H7: Relatório Final: até 48h após último documento. | I7: N/A | J7: Indexar DRL/documentos em todos os sinistros. | K7: Atualização de sinistro a cada 7 dias (portal aceita 9–11 dias). | L7: N/A | M7: Conforme apólice / prejuízo apurado. | N7: Jira (salvados) quando aplicável. | O7: N/A | P7: N/A | Q7: N/A | R7: Envio de RF e anexos via portal (PDF). | S7: Formatação PDF obrigatória; sem vídeos/áudios/ZIP. | T7: N/A | U7: Não clicar na “Caixa de Notificações” do portal; registrar todas tratativas por e-mail e indexar no portal.
A8: TOKIO MARINE – Judicial | B8: Portal Parceiros | C8: N/A | D8: N/A | E8: 1º contato: 24h; agendamento: imediato (se aplicável). | F8: N/A | G8: 7 dias (Relatório Preliminar). | H8: 7 dias após último documento (Relatório Final). | I8: N/A | J8: N/A | K8: N/A | L8: 365 dias (Prazo regular de regulação). | M8: Conforme apólice / prejuízo apurado. | N8: N/A | O8: N/A | P8: N/A | Q8: Processos por hora: TS até 30 dias para aprovação (quando aplicável). | R8: N/A | S8: N/A | T8: N/A | U8: —
A9: TOKIO MARINE – RCF-V | B9: Sem acesso ao sistema; tratativas por e-mail | C9: N/A | D9: Sim — copiar analista responsável; e, em faturamento/kit, incluir raquel.lopes@tokiomarine.com.br. | E9: Abertura: 2h; 1º contato: 24h; agendamento: 24h. | F9: N/A | G9: Reporte/Preliminar: 24h (após análise inicial). | H9: Relatório Final: 5 dias após documentação. | I9: N/A | J9: N/A | K9: Reiterações: 7 dias. | L9: Encerramento: 30 dias (regular). | M9: Conforme apólice / prejuízo apurado. | N9: N/A | O9: N/A | P9: N/A | Q9: Processos sempre por hora; TS deve ser salvo e enviado com o kit (não precisa aprovação). | R9: Envios de kit por e-mail; copiar raquel.lopes@tokiomarine.com.br. | S9: N/A | T9: N/A | U9: Enviar planilha de envios dia 20 p/ Raquel; não usar portal para faturamento (RCF-V).
A10: SANCOR – Judicial | B10: N/A | C10: N/A | D10: N/A | E10: Abertura: 24h; 1º contato: 24h; agendamento: imediato. | F10: N/A | G10: Preliminar: 48h após análise dos documentos. | H10: Final: 5 dias após recebimento do último documento. | I10: N/A | J10: N/A | K10: Reiterações: a cada 7 dias. | L10: Prazo regular de regulação: 365 dias. | M10: Conforme apólice / prejuízo apurado. | N10: N/A | O10: N/A | P10: N/A | Q10: N/A | R10: N/A | S10: N/A | T10: N/A | U10: — | Y10: Todos os pedidos de aprovação de timesheet devem ser encaminhados ao analista responsável, com o endereço sinistrosdespesas@fatorseguradora.com.br em cópia.
A11: SOMPO - RCV | B11: N/A | C11: N/A | D11: É necessário incluir em cópia oculta o endereço docsinistrotransportes@sompo.com.br | E11: No máximo 24h após o aviso | F11: N/A | G11: N/A | H11: 07 dias úteis, mas buscando a possibilidade de reduzir em 5 dias úteis | I11: N/A | J11: N/A | K11: N/A | L11: 07 dias úteis, mas buscando a possibilidade de reduzir em 5 dias úteis | M11: Conforme apólice / prejuízo apurado. | N11: N/A | O11: N/A | P11: N/A | Q11: N/A | R11: N/A | S11: N/A | T11: N/A | V11: N/A | Y11: SLA DE ANÁLISE: Após o recebimento do relatório da Addvalora, o analista Sompo terá 05 dias úteis para passar o parecer ao analista da Corretora e pedir a documentação necessária para indenização ou alinhar possível negativa. SLA DE INDENIZAÇÃO: Inicia-se após o analista Sompo receber os documentos necessários da Corretora para programar o pagamento da Indenização. 03 dias úteis a contar da data do recebimento da documentação exigida, incluindo: Documentação SUSEP, Termo de Quitação e Comprovante de pagamento do Segurado ao Terceiro, para que o beneficiário seja indenizado conforme a cobertura contratada. Em relação aos documentos necessásrios para regulação / análise dos Sinistros: DOCUMENTAÇÃO PADRÃO A SER SOLICITADA: Documentos Segurado i. Boletim de Ocorrência (B.O.); ii. CNH do Condutor no momento do acidente; iii.CRLV do Veículo Segurado; iv. Aviso de sinistro do segurado (detalhando o evento e sua responsabilidade sobre a ocorrência); v. * Documentos do embarque: Nota fiscal da carga e Conhecimento de Transportes (CTe) e Manifesto de carga. *documento necessário para consulta da averbação. Documentos Terceiro (Vítima do Dano) i. CRLV do veículo do terceiro (se aplicável); ii. CNH do condutor do veículo terceiro (no momento do acidente) (se aplicável); iii. Laudo de vistoria do veículo (emitido por oficina referenciada ou perito da seguradora) (se aplicável); iv. Orçamento(s) do conserto do bem danificado (pelo menos 2 orçamentos); v. Notas fiscais dos serviços e/ou peças, caso o conserto já tenha sido efetuado; vi. Dados bancários para reembolso / pagamento / Termo SUSEP OBS.: Este é um seguro de reembolso. O pagamento ocorre ao segurado após comprovação do pagamento efetuado por ele. Pagamentos a terceiros apenas com autorização do segurado. Documentos em caso de Perda Total do Veículo (para transferência para Sompo): - IPVA quitado; - DPVAT quitado; - Licenciamento quitados; - Multas quitadas ou “NADA CONSTA DO VEÍCULO”; e - Baixa do gravame (se o veículo for financiado). 1. Documentos Danos Corporais ou Morais i. Prontuários médicos; ii. Laudos ou atestados médicos; iii. Notas fiscais de despesas médicas; iv. Comprovantes de afastamento ou perda de renda (se aplicável); v. Documentos pessoais da vítima (RG, CPF, etc.); vi. Receituários Médicos (para os medicamentos); vii. Danos Corporais – Morte ou Invalidez; viii. Laudo do IML e Atestado de óbito (em caso de morte); ix. Certidão Atualizada de nascimento e/ou casamento (em caso de morte); x. Contato e e-mail do representante do terceiro. 1. Documentos para indenização i. Cópia do Contrato Social e última alteração; ii. Cópia do cartão CNPJ; iii. Comprovante de endereço atualizado (com até 03 meses); iv. Cópia dos documentos dos sócios da empresa constante no Contrato Social ou Procuração e documentos outorgando o representante legal da empresa; v. Documentos pessoais (Pessoa Física) vi. Termo Susep vii. Termo de quitação do terceiro. OBSERVAÇÃO IMPORTANTE: Ao receber documentos dos terceiros e/ou segurados, a Addvalora, no caso dos processos da AON, irá incluí-los no sistema da corretora (Aon - Web)."
A12: SOMPO – ADM | B12: N/A | C12: N/A | D12: Copiar docsinistrore@sompo.com.br nas tratativas. | E12: N/A (contato rápido); agendamento imediato quando aplicável. | F12: N/A | G12: N/A | H12: N/A | I12: N/A | J12: N/A | K12: N/A | L12: Até 120 dias (regulação), quando aplicável. | M12: Conforme apólice / prejuízo apurado. | N12: N/A | O12: N/A | P12: N/A | Q12: Timesheet aprovado antes do faturamento (quando aplicável). | R12: N/A | S12: N/A | T12: N/A | U12: Atualizar planilha de lote quando aplicável; alguns casos com análise terceirizada (e-mail sompo).
A13: ZURICH – ADM | B13: SOL – https://internet2.minasbrasil.com.br/SinistroOnLine/Login.aspx | C13: N/A | D13: Sim – comunicar analista por e-mail após inserir o Kit. | E13: Até 3h da contratação; agendamento imediato. | F13: 3 dias após vistoria/documentos. | G13: 72h após vistoria ou docs iniciais. | H13: 7 dias após último documento (10 se houver perícia). | I13: N/A | J13: N/A | K13: 15 dias. | L13: 120 dias. | M13: Conforme apólice / prejuízo apurado. | N13: N/A | O13: N/A | P13: Sim — enviar demonstrativo no Kit Faturamento. | Q13: Sim — após aprovação do TS. | R13: Sim — enviar relatório final + kit no sistema e por e-mail. | S13: N/A | T13: N/A | U13: Inserir código '22' no nome do Kit; print do protocolo no Baruc; TS aprovado antes; hospedagem 3★; alimentação R$25; deslocamento R$1/km.
A14: ZURICH – ADM – Pepper | B14: SOL – https://internet2.minasbrasil.com.br/SinistroOnLine/Login.aspx | C14: N/A | D14: Sim – comunicar analista por e-mail após inserir o Kit. | E14: Até 24h da contratação; agendamento imediato. | F14: 3 dias após vistoria/documentos. | G14: 7 dias úteis após vistoria ou docs iniciais. | H14: 7 dias após último documento (10 se houver perícia). | I14: N/A | J14: N/A | K14: 15 dias. | L14: 75 dias ou 5 reiterações. | M14: Conforme apólice / prejuízo apurado. | N14: N/A | O14: N/A | P14: Sim — enviar demonstrativo no Kit Faturamento. | Q14: Sim — após aprovação do TS. | R14: Sim — enviar relatório final + kit no sistema e por e-mail. | S14: N/A | T14: N/A | U14: Mesmas regras da Zurich; código '22' no Kit; DRL/Interino em 7 dias; hospedagem 3★; alimentação R$25; deslocamento R$1/km.

Sheet RCP (SLA)
A1: Seguradora | B1: Sistema | C1: Trocar campo de assunto do e-mail | D1: Copiar o analista em todos os e-mails | E1: SLA - 1º Contato e agendamento vistoria | F1: SLA- Realização da vistoria / Síntese | G1: SLA - Relatório Preliminar | H1: SLA - Relatório Final | I1: Relatório de regulação modelo próprio | J1: Cronologia no relatório (sugestão utilizar em todos os processos) | K1: Períodos para reiterações de documentos (SLA) | L1: Prazo de encerramento sem manifestação / documentos- (Cycle Time) | M1: Depreciação | N1: Valor em Risco | O1: Salvados | Q1: Apresentação da apuração ao segurado antes da seguradora analisar os valores | R1: Emissão termo de acordo / demonstrativo de prejuízos | U1: Precisa enviar relatório final junto com time sheet / despesas | V1: Envio do relatório final junto com a nota fiscal | W1: Formulários Próprios | X1: Emissão carta de encerramento / Negativa | Z1: Outros procedimentos e assuntos
M2: Reter a D.V.N | O2: Área de Salvados | P2: Sistema | R2: Regulação | S2: Seguradora | T2: Modelo próprio | X2: Regulação | Y2: Seguradora
A3: AKAD | B3: TYR - https://tyr.akadseguros.com.br/claim | C3: Não — campo de assunto não deve ser alterado. | D3: Não | E3: 24h abertura / contato com segurado. | F3: N/A | G3: 48h após acionamento. | H3: 5 dias úteis após último documento. | I3: N/A | J3: Sim | K3: Reiteração a cada 5 dias úteis (total de 14 reiterações) | L3: 70 dias (prazo regular de regulação). | M3: Conforme apólice / prejuízo apurado. | N3: 10 % remoto/30% possível/55% provável | O3: N/A | P3: N/A | Q3: N/A | R3: Sim — relatório final | S3: N/A | T3: Sim | U3: Não | V3: Não | W3: Sim | X3: regulação elabora e envia através | Y3: N/A | Z3: Hora/H Até 100K De 100k até 150k (17H) R$ 150,00 17 horas sem limitador
A4: AXA | B4: GIS– https://sinistro.axa.com.br/Portal/Base/Login/LoginPortal.aspx | C4: Não — campo de assunto não deve ser alterado. | D4: Sim - henrique.zolli@axa.com e caique.damasceno@axa.com | E4: 24h abertura / contato com segurado. | F4: N/A | G4: 5 dias úteis | H4: 5 dias úteis após último documento. | I4: Modelo Addvalora no padrão AXA. | J4: Sim | K4: Reiteração a cada 15 dias úteis (total de 3 reiterações) | L4: 45 dias (prazo regular de regulação). | M4: Conforme apólice / prejuízo apurado. | N4: 10 % remoto/40% possível/80% provável | O4: N/A | P4: N/A | Q4: N/A | R4: Sim — relatório final | S4: N/A | T4: Carta de encerramento emitida pela Cia. | U4: Sim | V4: Sim | W4: Sim | X4: regulação elabora | Y4: seguradora envia | Z4: Hora/H Até 40K De 40k até 80k De 80k até 120k Acima de 120k R$ 170,00 R$ 1.783,30 R$ 2.517,60 R$ 3.671,50 R$ 4.720,50
A5: EXCELSIOR – RCP | B5: N/A | C5: N/A | D5: N/A | E5: N/A | F5: N/A | G5: N/A | H5: 7 dias úteis após último documento. | I5: N/A | J5: N/A | K5: N/A | L5: N/A | M5: Conforme apólice / prejuízo apurado. | N5: Conforme apólice / prejuízo apurado. | O5: N/A | P5: N/A | Q5: N/A | R5: N/A | S5: N/A | T5: N/A | V5: N/A | W5: N/A | X5: N/A | Y5: N/A
A6: FAIRFAX – RCP | B6: FF ID - https://ffid.fairfax.com.br/login | C6: Não — campo de assunto não deve ser alterado. | D6: Sim — copiar sin-rc@fairfax.com.br e analista responsável. Final par Camilla, final ímpar David. | E6: N/A | F6: N/A | G6: N/A | H6: 7 dias úteis após últimos documentos. | I6: Modelo Addvalora no padrão Fairfax. | J6: Sim | K6: 1ª Reiteração 7 dias 2ª Reiteração 7 dias 3ª Reiteração 15 dias | L6: 45 dias (prazo regular de regulação). | M6: Conforme apólice / prejuízo apurado. | N6: 20 % remoto/80% possível/81% provável | O6: N/A | P6: N/A | Q6: N/A | R6: Sim — relatório final | S6: N/A | T6: Carta de encerramento emitida pela Cia. | U6: Não | V6: N/A | W6: DRL com cópia para sin-rc@fairfax.com.br; fechamento após 45 dias. | X6: regulação elabora | Y6: seguradora envia | Z6: Hora/H Expectativa (1H) Até 100K (10H) De 100k até 150k (17H) Acima de 150k (27H) RCPM R$ 150,00 R$ 150,00 R$ 1.500,00 R$ 2.550,00 R$ 4.050,00 R$ 600,00
A7: KOVR – RCP | B7: N/A | C7: N/A | D7: Sim — copiar sinistro.responsabilidades@kovr.com.br em todos os e-mails. | E7: 24h abertura / contato com segurado. | F7: N/A | G7: 48h após acionamento. | H7: 7 dias úteis após último documento. | I7: N/A | J7: N/A | K7: 1ª reiteração 7 dias; 2ª 14 dias; 3ª 21 dias + 7 dias p/ encerramento. | L7: 45 dias (prazo regular de regulação). | M7: Conforme apólice / prejuízo apurado. | N7: Conforme apólice / prejuízo apurado. | O7: N/A | P7: N/A | Q7: N/A | R7: N/A | S7: N/A | T7: Sim — carta de encerramento pode ser emitida pelo regulador. | W7: N/A | X7: N/A | Y7: N/A
A8: PORTO SEGURO – RCP | B8: Portal de Negócios – https://wwws.portoseguro.com.br/portalnegocio/ | C8: Não — campo de assunto não deve ser alterado. | D8: Não | E8: 24h abertura e contato com segurado/corretor. | F8: N/A | G8: email técnico até 10 dias úteis (sinistros > R$100k). | H8: 5 dias úteis após último documento. | I8: N/A | J8: N/A | K8: Reiterações: 7/7/7/7 dias | L8: 30 dias (prazo regular de regulação). | M8: Conforme apólice / prejuízo apurado. | N8: 30 % remoto/60% possível/90% provável | O8: N/A | P8: N/A | Q8: N/A | R8: Sim — relatório final | S8: N/A | T8: Sim | U8: Sim | V8: Sim | W8: Sim | X8: regulação elabora e envia através do triade | Y8: N/A | Z8: Hora/H limitado a R$ 150,00 20 horas
A9: SOMBRERO – RCP | B9: N/A | C9: N/A | D9: Sim — copiar analistas (rodrigo.coelho, karina.calamita, daniel.pauli@sombreroseguros.com.br). | E9: 24h abertura e contato com segurado/corretor. | F9: N/A | G9: 48h após acionamento. | H9: 7 dias úteis após últimos documentos. | I9: N/A | J9: N/A | K9: Reiterações a cada 15 dias (6 ciclos + 15 dias p/ encerramento). | L9: 90 dias (prazo regular de regulação). | M9: Conforme apólice / prejuízo apurado. | N9: Conforme apólice / prejuízo apurado. | O9: N/A | P9: N/A | Q9: N/A | R9: N/A | S9: N/A | T9: Sim — carta de encerramento emitida pelo regulador. | U9: Não | W9: N/A | X9: N/A | Y9: N/A

Sheet Garantia Judicial
A1: Seguradora | B1: Sistema | C1: Trocar campo de assunto do e-mail | D1: Copiar o analista em todos os e-mails | E1: SLA - 1º Contato e agendamento vistoria | F1: SLA- Realização da vistoria / Síntese | G1: SLA - Relatório Preliminar | H1: SLA - Relatório Final | I1: Relatório de regulação modelo próprio | J1: Cronologia no relatório (sugestão utilizar em todos os processos) | K1: Períodos para reiterações de documentos (SLA) | L1: Prazo de encerramento sem manifestação / documentos- (Cycle Time) | M1: Depreciação | N1: Valor em Risco | O1: Salvados | Q1: Apresentação da apuração ao segurado antes da seguradora analisar os valores | R1: Emissão termo de acordo / demonstrativo de prejuízos | U1: Precisa enviar relatório final junto com time sheet / despesas | V1: Envio do relatório final junto com a nota fiscal | W1: Formulários Próprios | X1: Emissão carta de encerramento / Negativa | Z1: Outros procedimentos e assuntos
M2: Reter a D.V.N | O2: Área de Salvados | P2: Sistema | R2: Regulação | S2: Seguradora | T2: Modelo próprio | X2: Regulação | Y2: Seguradora
A3: BMG | B3: Sim | C3: Sem orientação a respeito, seguir padrão da Addvalora | D3: Sim | E3: Acusação de recebimento e inicio imediato da abertura | F3: 12 horas para contato com o Tomador/Corretor após o recebimento do acionamento do sinistro | G3: 48 horas úteis para contato com a Cia após o recebimento do acionamento do sinistro | H3: Após o pagamento por parte da Cia ou a negativa no processo de regulação | I3: Sim | J3: Não aplicável | K3: A cada 2 dias | L3: 30 dias | M3: Não aplicável | N3: Não aplicável | O3: Não aplicável | P3: Não aplicável | Q3: Não aplicável | R3: Não aplicável | S3: Não aplicável | T3: Não aplicável | U3: Não | V3: Sem orientação a respeito | W3: Sem orientação a respeito | X3: Sim | Y3: Não | Z3: Layout dos Ofícios: Template Cia Requer aprovação da Cia.: Não Cópia nas tratativas internas (Reguladora e Cia): analista e documentos.sinistros@bmgseguros.com.br Cópia nas tratativas externas (Tomador, Corretor e Patrono): documentos.sinistros@bmgseguros.com.br Ofícios – e-mails para recebimento de intimações: documentos.sinistros@bmgseguros.com.br e garantiajudicial@addvaloaglobal.com Carta de Provisionamento: obrigatória para indenizações acima de R$ 100.000,00 Prazo para envio do Provisionamento: D-3 Ressarcimento: não aplicável (com contrato) Sistema da Seguradora: Pipefy (dependente do pedido do analista)
A4: Essor | B4: Não | C4: Sem orientação a respeito, seguir padrão da Addvalora | D4: Sim | E4: Acusação de recebimento e inicio imediato da abertura | F4: 12 horas para contato com o Tomador/Corretor após o recebimento do acionamento do sinistro | G4: 48 horas úteis para contato com a Cia após o recebimento do acionamento do sinistro | H4: Após o pagamento por parte da Cia ou a negativa no processo de regulação | I4: Sim | J4: Não aplicável | K4: A cada 2 dias | L4: 30 dias | M4: Não aplicável | N4: Não aplicável | O4: Não aplicável | P4: Não aplicável | Q4: Não aplicável | R4: Não aplicável | S4: Não aplicável | T4: Não aplicável | U4: Não | V4: Sem orientação a respeito | W4: Sem orientação a respeito | X4: Sim | Y4: Não | Z4: Layout dos Ofícios: Template Cia Requer aprovação da Cia.: Não Cópia nas tratativas internas (Reguladora e Cia.):brayssa.bercot@essor.com.br, sinistro.garantia@essor.com.br Em casos acima de R$ 200.000,00, incluir também: marcio.fetal@essor.com.br Cópia nas tratativas externas (Tomador, Corretor, Patrono): sinistro.garantia@essor.com.br Ofícios – e-mails para recebimento de intimações:sinistro.garantia@essor.com.br garantiajudicial@addvaloraglobal.com Carta de Provisionamento: Indenizações acima de R$ 200.000,00 Prazo para envio do Provisionamento: D-3 Ressarcimento: Sim Sistemas de Seguradoras:Não
A5: Excelsior | B5: Sim | C5: Sem orientação a respeito, seguir padrão da Addvalora | D5: Sim | E5: Acusação de recebimento e inicio imediato da abertura | F5: 12 horas para contato com o Tomador/Corretor após o recebimento do acionamento do sinistro | G5: 48 horas úteis para contato com a Cia após o recebimento do acionamento do sinistro | H5: Após o pagamento por parte da Cia ou a negativa no processo de regulação | I5: Sim | J5: Não aplicável | K5: A cada 2 dias | L5: 30 dias | M5: Não aplicável | N5: Não aplicável | O5: Não aplicável | P5: Não aplicável | Q5: Não aplicável | R5: Não aplicável | S5: Não aplicável | T5: Não aplicável | U5: Não | V5: Sem orientação a respeito | W5: Sem orientação a respeito | X5: Sim | Y5: Não | Z5: Layout dos Ofícios: Template Cia Requer aprovação da Cia.: Não Cópia nas tratativas internas (Reguladora e Cia.): guilherme.otilio@excelsiorseguros.com.br, controladoria.dejur@excelsiorseguros.com.br marcos.dias@excelsiorseguros.com.br Cópia nas tratativas externas (Tomador, Corretor, Patrono): controladoria.dejur@excelsiorseguros.com.br Ofícios – e-mails para recebimento de intimações: marcos.dias@excelsiorseguros.com.br, controladoria.dejur@excelsiorseguros.com.br e garantiajudicial@addvaloraglobal.com Carta de Provisionamento: Sim Prazo para envio do Provisionamento: D-3 Ressarcimento: Sim Sistemas de Seguradoras: GR5
A6: Sombrero | B6: Sim | C6: Sem orientação a respeito, seguir padrão da Addvalora | D6: Sim | E6: Acusação de recebimento e inicio imediato da abertura | F6: 12 horas para contato com o Tomador/Corretor após o recebimento do acionamento do sinistro | G6: 48 horas úteis para contato com a Cia após o recebimento do acionamento do sinistro | H6: Após o pagamento por parte da Cia ou a negativa no processo de regulação | I6: Sim | J6: Não aplicável | K6: A cada 2 dias | L6: 30 dias | M6: Não aplicável | N6: Não aplicável | O6: Não aplicável | P6: Não aplicável | Q6: Não aplicável | R6: Não aplicável | S6: Não aplicável | T6: Não aplicável | U6: Não | V6: Sem orientação a respeito | W6: Sem orientação a respeito | X6: Sim | Y6: Não | Z6: Layout dos Ofícios: Template Cia Requer Aprovação da Cia.: Sim (teses novas) Quem copiar nas tratativas internas (Reguladora e Cia.): Para e-mails de rotina e pedidos de documentos (apólice, CCG, informações comerciais etc.): sinistros.garantia@sombreroseguros.com.br Para e-mails de tomada de decisão: daniel.pauli@sombreroseguros.com.br, leticia.maso@sombreroseguros.com.br, maria.monteiro@sombreroseguros.com.br, sinistros.garantia@sombreroseguros.com.br e barbara.nascimento@sombreroseguros.com.br Quem copiar nas tratativas externas (Tomador, Corretor, Patrono): sinistros.garantia@sombreroseguros.com.br Nos ofícios, colocar os seguintes e-mails para recebimento de intimação: sinistros.garantia@sombreroseguros.com.br e garantiajudicial@addvaloraglobal.com Carta de Provisionamento: Indenizações acima de 100k Prazo de Envio do Provisionamento: D-3 Ressarcimento: Sim (necessita de autorização) Sistemas de Seguradoras: Sim – Gclaims
A7: Sompo | B7: Não | C7: Sem orientação a respeito, seguir padrão da Addvalora | D7: Sim | E7: Acusação de recebimento e inicio imediato da abertura | F7: 12 horas para contato com o Tomador/Corretor após o recebimento do acionamento do sinistro | G7: 48 horas úteis para contato com a Cia após o recebimento do acionamento do sinistro | H7: Após o pagamento por parte da Cia ou a negativa no processo de regulação | I7: Sim | J7: Não aplicável | K7: A cada 2 dias | L7: 30 dias | M7: Não aplicável | N7: Não aplicável | O7: Não aplicável | P7: Não aplicável | Q7: Não aplicável | R7: Não aplicável | S7: Não aplicável | T7: Não aplicável | U7: Não | V7: Sem orientação a respeito | W7: Sem orientação a respeito | X7: Sim | Y7: Não | Z7: Layout dos Ofícios Template Cia Requer aprovação da Cia. Não Quem copiar nas tratativas internas (Reguladora e Cia.) flspio@sompo.com.br, epsantos@sompo.com.br e sinistrocorporativo@sompo.com.br Quem copiar nas tratativas externas (Tomador, Corretor, Patrono) flspio@sompo.com.br, sinistrocorporativo@sompo.com.br Nos ofícios, colocar os seguintes e-mails para recebimento de intimação sinistrocorporativo@sompo.com.br e garantiajudicial@addvaloraglobal.com Carta de Provisionamento Sim Prazo de Envio do Provisionamento D-3 Ressarcimento Não Sistemas de Seguradoras Não

Sheet Garantia - Ressarcimento
A1: Seguradora | B1: Sistema | C1: Trocar campo de assunto do e-mail | D1: Copiar o analista em todos os e-mails | E1: SLA - 1º Contato e agendamento vistoria | F1: SLA- Realização da vistoria / Síntese | G1: SLA - Relatório Preliminar | H1: SLA - Relatório Final | I1: Relatório de regulação modelo próprio | J1: Cronologia no relatório (sugestão utilizar em todos os processos) | K1: Períodos para reiterações de documentos (SLA) | L1: Prazo de encerramento sem manifestação / documentos- (Cycle Time) | M1: Depreciação | N1: Valor em Risco | O1: Salvados | Q1: Apresentação da apuração ao segurado antes da seguradora analisar os valores | R1: Emissão termo de acordo / demonstrativo de prejuízos | U1: Precisa enviar relatório final junto com time sheet / despesas | V1: Envio do relatório final junto com a nota fiscal | W1: Formulários Próprios | X1: Emissão carta de encerramento / Negativa | Z1: Outros procedimentos e assuntos
M2: Reter a D.V.N | O2: Área de Salvados | P2: Sistema | R2: Regulação | S2: Seguradora | T2: Modelo próprio | X2: Regulação | Y2: Seguradora
A3: Sombrero | B3: Sim | C3: Sem orientação a respeito Seguir padrão da Addvalora | D3: Sim | E3: Acusação de recebimento e inicio imediato da abertura | F3: 5 dias uteis para elaboração da notificação extrajudicial | G3: Não aplicável | H3: Não aplicável | I3: Sim | J3: Não aplicável | K3: Não aplicável | L3: Não aplicável | M3: Não aplicável | N3: Não aplicável | O3: Não aplicável | P3: Não aplicável | Q3: Não aplicável | R3: Não aplicável | S3: Não aplicável | T3: Não aplicável | U3: Não | V3: Não aplicável | W3: Não aplicável | X3: Sim | Y3: Não | Z3: Nota Fiscal na Notificação Extrajudicial: Não Duração do Ressarcimento Administrativo: 3 meses Layout dos Ofícios: Template Cia Requer Aprovação da Cia.: Não Tratativas com a Cia: daniel.pauli@sombreroseguros.com.br e maria.monteiro@sombreroseguros.com.br. Quem copiar nas tratativas externas (Tomador, Corretor, Patrono): maria.monteiro@sombreroseguros.com.br. Reenvio para novos endereços – Requer aprovação da Cia.: Sim Termo de Confissão de Dívida – Requer validação da Cia.: Sim Conferência de Crédito: maria.monteiro@sombreroseguros.com.br. Sistemas de Seguradoras: Sim – Gclaims
A4: Essor | B4: Não | C4: Sem orientação a respeito Seguir padrão da Addvalora | D4: Sim | E4: Acusação de recebimento e inicio imediato da abertura | F4: 5 dias uteis para elaboração da notificação extrajudicial | G4: Não aplicável | H4: Não aplicável | I4: Sim | J4: Não aplicável | K4: Não aplicável | L4: Não aplicável | M4: Não aplicável | N4: Não aplicável | O4: Não aplicável | P4: Não aplicável | Q4: Não aplicável | R4: Não aplicável | S4: Não aplicável | T4: Não aplicável | U4: Não aplicável | V4: Não aplicável | W4: Não aplicável | X4: Sim | Y4: Não | Z4: Nota Fiscal na Notificação Extrajudicial: Não Duração do Ressarcimento Administrativo: 3 meses Layout dos Ofícios: Template Cia Requer Aprovação da Cia.: Não Quem copiar nas tratativas internas (Reguladora e Cia.): ressarcimento@essor.com.br ; francisco.pereira@essor.com.br; sinistro.garantia@essor.com.br Quem copiar nas tratativas externas (Tomador, Corretor, Patrono): sinistro.garantia@essor.com.br Reenvio para novos endereços – Requer aprovação da Cia.: Não Termo de Confissão de Dívida – Requer validação da Cia.: Não Conferência de Crédito: ressarcimento@essor.com.br Ressarcimento Judicializado: rebecahilcko@hilckoehey.com.br; lucianahey@hilckoehey.com.br; taissaalmeida@hilckoehey.com.br; danilowosch@hilckoehey.com.br ; kauanegoncalves@hilckoehey.com.br
A5: Excelsior | B5: Sim | C5: Sem orientação a respeito Seguir padrão da Addvalora | D5: Sim | E5: Acusação de recebimento e inicio imediato da abertura | F5: 5 dias uteis para elaboração da notificação extrajudicial | G5: 48 horas úteis para contato com a Cia após o recebimento do acionamento do sinistro | H5: Após o pagamento por parte da Cia ou a negativa no processo de regulação | I5: Sim | J5: Não aplicável | K5: 30 dias | M5: Não aplicável | N5: Não aplicável | O5: Não aplicável | P5: Não aplicável | Q5: Não aplicável | R5: Não aplicável | S5: Não aplicável | T5: Não aplicável | U5: Não | V5: Sem orientação a respeito | W5: Sem orientação a respeito | X5: Sim | Y5: Não | Z5: Nota Fiscal na Notificação Extrajudicial: Sim Duração do Ressarcimento Administrativo: 3 meses, exceto casos acima de 300K (1 mês) Layout dos Ofícios: Template Cia Requer Aprovação da Cia.: Não Quem copiar nas tratativas internas (Reguladora e Cia.): controladoria.dejur@excelsiorseguros.com.br Quem copiar nas tratativas externas (Tomador, Corretor, Patrono): controladoria.dejur@excelsiorseguros.com.br Reenvio para novos endereços – Requer aprovação da Cia.: Sim Termo de Confissão de Dívida – Requer validação da Cia.: Sim Conferência de Crédito: angelita.campelo@excelsiorseguros.com.br Ressarcimento Judicializado: rebecahilcko@hilckoehey.com.br; lucianahey@hilckoehey.com.br ; taissaalmeida@hilckoehey.com.br ; danilowosch@hilckoehey.com.br ; kauanegoncalves@hilckoehey.com.br

Sheet Garantia - Adicional Trabalhist
A1: Seguradora | B1: Sistema | C1: Trocar campo de assunto do e-mail | D1: Copiar o analista em todos os e-mails | E1: SLA - 1º Contato e agendamento vistoria | F1: SLA- Realização da vistoria / Síntese | G1: SLA - Relatório Preliminar | H1: SLA - Relatório Final | I1: Relatório de regulação modelo próprio | J1: Cronologia no relatório (sugestão utilizar em todos os processos) | K1: Períodos para reiterações de documentos (SLA) | L1: Prazo de encerramento sem manifestação / documentos- (Cycle Time) | M1: Depreciação | N1: Valor em Risco | O1: Salvados | Q1: Apresentação da apuração ao segurado antes da seguradora analisar os valores | R1: Emissão termo de acordo / demonstrativo de prejuízos | U1: Precisa enviar relatório final junto com time sheet / despesas | V1: Envio do relatório final junto com a nota fiscal | W1: Formulários Próprios | X1: Emissão carta de encerramento / Negativa | Z1: Outros procedimentos e assuntos
M2: Reter a D.V.N | O2: Área de Salvados | P2: Sistema | R2: Regulação | S2: Seguradora | T2: Modelo próprio | X2: Regulação | Y2: Seguradora
A3: Avla | B3: Não | C3: Sem orientação a respeito, seguir padrão da Addvalora | D3: Apenas nas tratativas internas (Seguradora e Addvalora). | E3: Acusação de recebimento e inicio imediato da abertura | F3: 5 dias para contato com a Cia após o recebimento do acionamento do sinistro. | G3: 5 dias para contato com a Cia após o recebimento do acionamento do sinistro. | H3: 5 dias contados da autorização para emissão do Relatório Final pela Cia. | I3: Sim | J3: Não aplicável | K3: Após 30 dias corridos da solicitação. | L3: 30 dias corridos após a 2ª reiteração. | M3: Não aplicável | N3: Não aplicável | O3: Não aplicável | P3: Não aplicável | Q3: Não aplicável | R3: Não aplicável | S3: Não aplicável | T3: Não aplicável | U3: Não | V3: Sem orientação a respeito | W3: Sem orientação a respeito | X3: Sim | Y3: Não | Z3: Layout dos Ofícios: Template Cia. Forma de envio de correspondências: E-mail e formato PDF. Requer aprovação da Cia.: Sim, todas as cartas precisam ser validadas. Quem assina as cartas: Addvalora. Cópia nas tratativas internas (Reguladora e Cia): analista e Caixa Departamental sinistrobr.garantia@avla.com Cópia nas tratativas externas (Tomador, Corretor e Patrono): Caixa Departamental sinistrobr.garantia@avla.com Concessão de prazos ao Segurado e Tomador: 15 dias corridos. Carta de Provisionamento: Sim. Ressarcimento: não.
A4: Axa | B4: Não | C4: Sem orientação a respeito, seguir padrão da Addvalora | D4: Sim | E4: Acusação de recebimento e inicio imediato da abertura | F4: 5 dias para contato com a Cia após o recebimento do acionamento do sinistro. | G4: 5 dias para contato com a Cia após o recebimento do acionamento do sinistro. | H4: 5 dias contados da autorização para emissão do Relatório Final pela Cia. | I4: Sim | J4: Não aplicável | K4: Após 30 dias corridos da solicitação. | L4: 30 dias corridos após a 1ª reiteração. | M4: Não aplicável | N4: Não aplicável | O4: Não aplicável | P4: Não aplicável | Q4: Não aplicável | R4: Não aplicável | S4: Não aplicável | T4: Não aplicável | U4: Não | V4: Sem orientação a respeito | W4: Sem orientação a respeito | X4: Sim | Y4: Não | Z4: Layout dos Ofícios: Template Cia. Forma de envio de correspondências: E-mail (PDF) e Correios. Requer aprovação da Cia.: Sim, todas as cartas precisam ser validadas. Quem assina as cartas: Analista AXA. Cópia nas tratativas internas (Reguladora e Cia): analistas: claudia.morgado@axa.com; ingrid.machado@axa.com. Cópia nas tratativas externas (Tomador, Corretor e Patrono): analistas: claudia.morgado@axa.com; ingrid.machado@axa.com. Concessão de prazos ao Segurado e Tomador: 15 dias corridos. Carta de Provisionamento: Sim. Ressarcimento: não Reclamatória trabalhista: Monitoramento: a cada 90 dias. Analisar a fase do processo e se for preciso monitorar em menor tempo. Enviar parecer de atualização para a Cia dentro do prazo de 90 dias, mesmo que a reclamatória trabalhista não tenha movimentos relevantes.
A5: Berkley | B5: Sim | C5: Sem orientação a respeito, seguir padrão da Addvalora | D5: Sim | E5: Acusação de recebimento e inicio imediato da abertura | F5: 5 dias para contato com a Cia após o recebimento do acionamento do sinistro. | G5: 5 dias para contato com a Cia após o recebimento do acionamento do sinistro. | H5: 5 dias contados da autorização para emissão do Relatório Final pela Cia. | I5: Sim | J5: Não aplicável | K5: Após 30 dias corridos da solicitação. | L5: 30 dias corridos após a 2ª reiteração. | M5: Não aplicável | N5: Não aplicável | O5: Não aplicável | P5: Não aplicável | Q5: Não aplicável | R5: Não aplicável | S5: Não aplicável | T5: Não aplicável | U5: Não | V5: Sem orientação a respeito | W5: Sem orientação a respeito | X5: Sim | Y5: Não | Z5: Layout dos Ofícios: Template Cia. Forma de envio de correspondências: E-mail e formato PDF. Requer aprovação da Cia.: Sim, todas as cartas precisam ser validadas. Quem assina as cartas: Analista Cia. Cópia nas tratativas internas (Reguladora e Cia): aferreira@berkley.com.br; ltureck@berkley.com.br; pquignoli@berkley.com.br Cópia nas tratativas externas (Tomador, Corretor e Patrono): aferreira@berkley.com.br; ltureck@berkley.com.br; pquignoli@berkley.com.br Concessão de prazos ao Segurado e Tomador: 15 dias corridos. Carta de Provisionamento: Sim. Ressarcimento: não.
A6: Daycoval | B6: Sim | C6: Sem orientação a respeito, seguir padrão da Addvalora | D6: Apenas nas tratativas internas (Seguradora e Addvalora). | E6: Acusação de recebimento e inicio imediato da abertura | F6: 5 dias (casos normais) e 3 dias (casos urgentes) para contato com a Cia após o recebimento do acionamento do sinistro. | G6: 5 dias (casos normais) e 3 dias (casos urgentes) para contato com a Cia após o recebimento do acionamento do sinistro. | H6: 3 dias contados da autorização para emissão do Relatório Final pela Cia. | I6: Sim | J6: Não aplicável | K6: Não há reiteração. | L6: Não há reiteração. | M6: Não aplicável | N6: Não aplicável | O6: Não aplicável | P6: Não aplicável | Q6: Não aplicável | R6: Não aplicável | S6: Não aplicável | T6: Não aplicável | U6: Não | V6: Sem orientação a respeito | W6: Sem orientação a respeito | X6: Sim | Y6: Não | Z6: Forma de envio de correspondências e Formato do Conteúdo: Todos os pareceres e correspondências serão encaminhados unicamente por via digital, no corpo do e-mail; exceto o relatório final e a notificação de pagamento espontâneo ao Tomador, que serão assinados por certificação digital e transmitidos em PDF anexado ao e-mail. Mantêm-se a ressalva de que havendo necessidade de envio físico de correspondências, haverá um custo referente as despesas de postagem e monitoramento do retorno do AR, de R$ 50,00 por carta/endereço diligenciado. Monitoramento: Sim, semestral, com reporte via planilha do Excel. Fluxo de atendimento padrão: 1. Recebimento da expectativa via Pipefy 2. Análise inicial da Reclamatória Trabalhista (apuração de informações mínimas para apreciação de eventual cobertura, p. ex.: Local de Prestação de Serviço, Função, Jornada, Último Salário, Período Laborado, Pedidos e etc) em contraponto com a apólice emitida; 3. Elaboração e envio de correspondências iniciais ao Segurado e ao Tomador, formalizando o registro da expectativa de sinistro e destacando o dever de manterem a Cia. atualizada sobre seus trâmites; 4. Confecção de parecer para a Cia. compilando as informações coletadas, incluindo a fase do processo trabalhista; 5. Suspensão da expectativa nos registros da Reguladora e da Seguradora (card irá para fase "reclamatória trabalhista em andamento"). 6. Faturamento dos honorários; 7. Monitoramento semestral com reporte via planilha Excel. Caso seja identificado o pagamento da condenação pelo Segurado: Se, nos monitoramentos periódicos, apurar-se a realização de pagamento de condenação pelo Segurado, a situação será reportada à Cia. para acompanhamento do prazo prescricional ânuo (o card migrará para a fase “Ag. Prazo Prescricional”), porém, não haverá a automática convolação da expectativa em sinistro, o que dependerá da formalização de reclamação de sinistro pelo Segurado, solicitando o respectivo reembolso, a partir do qual se adotará o seguinte fluxo: 1. Formalização de reclamação de sinistro pelo Segurado; 2. Solicitação de documentos adicionais, se houver necessidade, seguido de análise completa; emissão de parecer de convolação à Cia. e de notificação de pagamento espontâneo ao Tomador; elaboração do relatório final simplificado e envio ao Segurado (após validação da Cia.); 3. Acompanhamento do retorno do TQP, validação dos documentos de representação e envio para programação de pagamento; 4. Recepção do comprovante de pagamento fornecido pela Cia. e encaminhamento do Segurado; 5. Encerramento da regulação com enfrentamento de mérito.
A7: Essor | B7: Sim | C7: Sem orientação a respeito, seguir padrão da Addvalora | D7: Apenas nas tratativas internas (Seguradora e Addvalora). | E7: Acusação de recebimento e inicio imediato da abertura | F7: 5 dias para contato com a Cia após o recebimento do acionamento do sinistro. | G7: 5 dias para contato com a Cia após o recebimento do acionamento do sinistro. | H7: 5 dias contados da autorização para emissão do Relatório Final pela Cia. | I7: Sim | J7: Não aplicável | K7: Após 30 dias corridos da solicitação. | L7: 30 dias corridos após a 2ª reiteração. | M7: Não aplicável | N7: Não aplicável | O7: Não aplicável | P7: Não aplicável | Q7: Não aplicável | R7: Não aplicável | S7: Não aplicável | T7: Não aplicável | U7: Não | V7: Sem orientação a respeito | W7: Sem orientação a respeito | X7: Sim | Y7: Não | Z7: Layout dos Ofícios: Template Cia. Forma de envio de correspondências: E-mail (PDF). O envio pelos correios ocorrerá apenas se não houver endereço eletrônico válido das partes, mediante prévia anuência da Seguradora. (em casos que o nosso limitador seja de até 10k, enviar no corpo do e-mail) Requer aprovação da Cia.: Apenas cartas estratégicas precisam ser validadas com o analista. Quem assina as cartas: Addvalora. Exceto: as cartas/RFR que encerramos o processo por negativa de pagamento de indenização devemos enviar à Seguradora para assinatura. Cópia nas tratativas internas (Reguladora e Cia): Analista Rayssa (rayssa.bercot@essor.com.br), com cópia para a Caixa departamental sinistro.garantia@essor.com.br. Cópia nas tratativas externas (Tomador, Corretor e Patrono): a Caixa departamental sinistro.garantia@essor.com.br. Concessão de prazos ao Segurado e Tomador: 15 dias corridos Carta de Provisionamento: As reservas devem seguir o seguinte critério: Remoto (R$ 1,00), Possível (35% do valor reclamado), Provável (100% do valor reclamado). No CPJ, nos casos que o provisionamento não seja 100%, devemos indicar o valor estimado conforme mencionado para a Cia, inserido no campo resultado a seguinte descrição: Exemplo: O valor da multa é de R$ 2.465,00, porém, conforme orientação da Seguradora, em se tratando de risco possível, indicamos a reserva de 35% do valor (R$ 862,75). Ressarcimento: Sim. Monitoramento: a cada 3 meses a depender do andamento da ação trabalhista e alinhamento com a cia.
A8: Excelsior | B8: Sim | C8: Sim. Seguir padrão da Excelsior. | D8: Apenas nas tratativas internas (Seguradora e Addvalora). | E8: Acusação de recebimento e inicio imediato da abertura | F8: 5 dias para contato com a Cia após o recebimento do acionamento do sinistro. | G8: 5 dias para contato com a Cia após o recebimento do acionamento do sinistro. | H8: 5 dias contados da autorização para emissão do Relatório Final pela Cia. | I8: Sim | J8: Não aplicável | K8: Após 30 dias corridos da solicitação. | L8: 30 dias corridos após a 2ª reiteração. | M8: Não aplicável | N8: Não aplicável | O8: Não aplicável | P8: Não aplicável | Q8: Não aplicável | R8: Não aplicável | S8: Não aplicável | T8: Não aplicável | U8: Não | V8: Sem orientação a respeito | W8: Sem orientação a respeito | X8: Sim | Y8: Não | Z8: Layout dos Ofícios: Template Cia. Forma de envio de correspondências: E-mail (PDF) e Correios. (em casos que o nosso limitador seja de até 10k, enviar no corpo do e-mail) Requer aprovação da Cia.: Apenas cartas estratégicas precisam ser validadas com o analista. Quem assina as cartas: Addvalora. Exceto: carta de negativa e baixa e relatório finais precisam ser assinados pela Cia. Cópia nas tratativas internas (Reguladora e Cia): gabriella.abreu@excelsiorseguros.com.br; fernanda.brito@excelsiorseguros.com.br; at@excelsiorseguros.com.br e a Caixa Departamental regulacao@excelsiorseguros.com.br. Cópia nas tratativas externas (Tomador, Corretor e Patrono): a Caixa departamental regulacao@excelsiorseguros.com.br. Concessão de prazos ao Segurado e Tomador: 15 dias corridos Carta de Provisionamento: Sim. Ressarcimento: Sim. Monitoramento da ação trabalhista: a cada 6 meses.
A9: HDI | B9: Não | C9: Sem orientação a respeito, seguir padrão da Addvalora | D9: Sim | E9: Acusação de recebimento e inicio imediato da abertura | F9: 5 dias para contato com a Cia após o recebimento do acionamento do sinistro. | G9: 5 dias para contato com a Cia após o recebimento do acionamento do sinistro. | H9: 5 dias contados da autorização para emissão do Relatório Final pela Cia. | I9: Sim | J9: Não aplicável | K9: Após 30 dias corridos da solicitação. | L9: Pendente de alinhamento. | M9: Não aplicável | N9: Não aplicável | O9: Não aplicável | P9: Não aplicável | Q9: Não aplicável | R9: Não aplicável | S9: Não aplicável | T9: Não aplicável | U9: Não | V9: Sem orientação a respeito | W9: Sem orientação a respeito | X9: Sim | Y9: Não | Z9: Layout dos Ofícios: Template Addvalora. Apenas Relatório Final e notificação para pagamento espontâneo seguem com a logo da Cia. Forma de envio de correspondências: E-mail (PDF). Requer aprovação da Cia.: Todas as cartas. Quem assina as cartas: Addvalora. Cópia nas tratativas internas (Reguladora e Cia): luciano.inovellini@br.hdi.global e janaina.duarte@br.hdi.global. Cópia nas tratativas externas (Tomador, Corretor e Patrono): luciano.inovellini@br.hdi.global e janaina.duarte@br.hdi.global.
A10: Pottencial | B10: Não | C10: Sem orientação a respeito, seguir padrão da Addvalora | D10: Sim | E10: Acusação de recebimento e inicio imediato da abertura | F10: 5 dias para contato com a Cia após o recebimento do acionamento do sinistro. | G10: 5 dias para contato com a Cia após o recebimento do acionamento do sinistro. | H10: 5 dias contados da autorização para emissão do Relatório Final pela Cia. | I10: Sim | J10: Não aplicável | K10: Após 30 dias corridos da solicitação. Necessário validação da Cia. | L10: 30 dias corridos após a 1ª reiteração. | M10: Não aplicável | N10: Não aplicável | O10: Não aplicável | P10: Não aplicável | Q10: Não aplicável | R10: Não aplicável | S10: Não aplicável | T10: Não aplicável | U10: Não | V10: Sem orientação a respeito | W10: Sem orientação a respeito | X10: Sim | Y10: Não | Z10: Para e-mails de rotina e pedidos de documentos (apólice, CCG, informações comerciais etc.): flavia.marchiori@pottencial.com.br; sinistro.terminodeobra@pottencial.com.br Em fluxo de reuniões, copiar também: debora.nunes@pottencial.com.br
A11: Sombrero | B11: Sim | C11: Sim, padrão Addvalora e acréscimo número apólice. | D11: Apenas nas tratativas internas (Seguradora e Addvalora). | E11: Acusação de recebimento e inicio imediato da abertura | F11: 5 dias para contato com a Cia após o recebimento do acionamento do sinistro. | G11: 5 dias para contato com a Cia após o recebimento do acionamento do sinistro. | H11: 5 dias contados da autorização para emissão do Relatório Final pela Cia. | I11: Sim | J11: Não aplicável | K11: Após 30 dias corridos da solicitação. | L11: 30 dias corridos após a 2ª reiteração. | M11: Não aplicável | N11: Não aplicável | O11: Não aplicável | P11: Não aplicável | Q11: Não aplicável | R11: Não aplicável | S11: Não aplicável | T11: Não aplicável | U11: Não | V11: Sem orientação a respeito | W11: Sem orientação a respeito | X11: Sim | Y11: Não | Z11: Layout dos Ofícios: Template Cia Formato do envio das correspondências: E-mails. Envio físico em casos pontuais com autorização da Cia. Requer Aprovação da Cia.: Correspondências de baixa, de negativa de indenização ou com posicionamento final da Seguradora - RFS (que envolva questões de mérito), precisam ser validadas. Correspondências de impulso processual e de baixa sem ônus à Sombrero (sem cunho decisório), dispensam validação prévia. Quem copiar nas tratativas internas (Reguladora e Cia.): Quando for necessário aprovação de cartas/pareceres/relatórios: direcionar o email para Maria Monteiro (maria.monteiro@sombreroseguros.com.br) com cópia para Leticia Maso (leticia.maso@sombreroseguros.com.br); • Solicitação de CCG do Tomador: Idália Soares (idalia.soares@sombreroseguros.com.br) com cópia para Maria Monteiro (maria.monteiro@sombreroseguros.com.br); • Solicitação de convolação/pagamento do sinistro ou encerramento da expectativa: Idália Soares (idalia.soares@sombreroseguros.com.br) com cópia para Maria Monteiro (maria.monteiro@sombreroseguros.com.br), Leticia Maso (leticia.maso@sombreroseguros.com.br) e Daniel De Pauli (daniel.pauli@sombreroseguros.com.br); • Trocas de emails com os Segurados e Tomadores: Incluir apenas o e-mail do Sinistros Garantia (sinistros.garantia@sombreroseguros.com.br); • Atualizações sobre os processos: Sinistros Garantia (sinistros.garantia@sombreroseguros.com.br). Quem copiar nas tratativas externas (Tomador, Corretor, Patrono): sinistros.garantia@sombreroseguros.com.br Nos ofícios, colocar os seguintes e-mails para recebimento de intimação: sinistros.garantia@sombreroseguros.com.br Carta de Provisionamento: Apenas em casos com sugestão de reserva acima de 100k. Abaixo desse valor, pode ser no corpo do e-mail. Ressarcimento: Sim (necessita de autorização) Sistemas de Seguradoras: Sim – Gclaims Monitoramento: a cada 90 dias. Analisar a fase do processo e a depender monitorar em menor tempo, podendo ser alinhado com a Cia.
A12: Sompo | B12: Não | C12: Sem orientação a respeito, seguir padrão da Addvalora | D12: Sim | E12: Acusação de recebimento e inicio imediato da abertura | F12: 5 dias para contato com a Cia após o recebimento do acionamento do sinistro. | G12: 5 dias para contato com a Cia após o recebimento do acionamento do sinistro. | H12: 5 dias contados da autorização para emissão do Relatório Final pela Cia. | I12: Sim | J12: Não aplicável | K12: Após 30 dias corridos da solicitação. | L12: 30 dias corridos após a 2ª reiteração. | M12: Não aplicável | N12: Não aplicável | O12: Não aplicável | P12: Não aplicável | Q12: Não aplicável | R12: Não aplicável | S12: Não aplicável | T12: Não aplicável | U12: Não | V12: Sem orientação a respeito | W12: Sem orientação a respeito | X12: Sim | Y12: Não | Z12: 1. Quando o processo envolver mais de um contrato e apólice SOMPO, iremos registrar uma expectativa/sinistro em cada apólice, mas com o envio de uma única correspondência. 2. Não é necessário fazer monitoramento das RTs. 3. Encerrar o processo de forma imediata após o envio das cartas (não precisa esperar nenhum retorno das partes nem AR).

Sheet Garantia - Executante
A1: Seguradora | B1: Sistema | C1: Trocar campo de assunto do e-mail | D1: Copiar o analista em todos os e-mails | E1: SLA - 1º Contato e agendamento vistoria | F1: SLA- Realização da vistoria / Síntese | G1: SLA - Relatório Preliminar | H1: SLA - Relatório Final | I1: Relatório de regulação modelo próprio | J1: Cronologia no relatório (sugestão utilizar em todos os processos) | K1: Períodos para reiterações de documentos (SLA) | L1: Prazo de encerramento sem manifestação / documentos- (Cycle Time) | M1: Depreciação | N1: Valor em Risco | O1: Salvados | Q1: Apresentação da apuração ao segurado antes da seguradora analisar os valores | R1: Emissão termo de acordo / demonstrativo de prejuízos | U1: Precisa enviar relatório final junto com time sheet / despesas | V1: Envio do relatório final junto com a nota fiscal | W1: Formulários Próprios | X1: Emissão carta de encerramento / Negativa | Z1: Outros procedimentos e assuntos
M2: Reter a D.V.N | O2: Área de Salvados | P2: Sistema | R2: Regulação | S2: Seguradora | T2: Modelo próprio | X2: Regulação | Y2: Seguradora
A3: Avla | B3: Não | C3: Sem orientação a respeito, seguir padrão da Addvalora | D3: Apenas nas tratativas internas (Seguradora e Addvalora). | E3: Acusação de recebimento e inicio imediato da abertura | F3: 5 dias para contato com a Cia após o recebimento do acionamento do sinistro. | G3: 5 dias para contato com a Cia após o recebimento do acionamento do sinistro. | H3: 5 dias contados da autorização para emissão do Relatório Final pela Cia. | I3: Sim | J3: Não aplicável | K3: Após 30 dias corridos da solicitação. | L3: 30 dias corridos após a 2ª reiteração. | M3: Não aplicável | N3: Não aplicável | O3: Não aplicável | P3: Não aplicável | Q3: Não aplicável | R3: Não aplicável | S3: Não aplicável | T3: Não aplicável | U3: Não | V3: Sem orientação a respeito | W3: Sem orientação a respeito | X3: Sim | Y3: Não | Z3: Layout dos Ofícios: Template Cia. Forma de envio de correspondências: E-mail e formato PDF. Requer aprovação da Cia.: Sim, todas as cartas precisam ser validadas. Quem assina as cartas: Addvalora. Cópia nas tratativas internas (Reguladora e Cia): analista e Caixa Departamental sinistrobr.garantia@avla.com Cópia nas tratativas externas (Tomador, Corretor e Patrono): Caixa Departamental sinistrobr.garantia@avla.com Concessão de prazos ao Segurado e Tomador: 15 dias corridos. Carta de Provisionamento: Sim. Ressarcimento: não.
A4: Axa | B4: Não | C4: Sem orientação a respeito, seguir padrão da Addvalora | D4: Sim | E4: Acusação de recebimento e inicio imediato da abertura | F4: 5 dias para contato com a Cia após o recebimento do acionamento do sinistro. | G4: 5 dias para contato com a Cia após o recebimento do acionamento do sinistro. | H4: 5 dias contados da autorização para emissão do Relatório Final pela Cia. | I4: Sim | J4: Não aplicável | K4: Após 30 dias corridos da solicitação. | L4: 30 dias corridos após a 1ª reiteração. | M4: Não aplicável | N4: Não aplicável | O4: Não aplicável | P4: Não aplicável | Q4: Não aplicável | R4: Não aplicável | S4: Não aplicável | T4: Não aplicável | U4: Não | V4: Sem orientação a respeito | W4: Sem orientação a respeito | X4: Sim | Y4: Não | Z4: Layout dos Ofícios: Template Cia. Forma de envio de correspondências: E-mail (PDF) e Correios. Requer aprovação da Cia.: Sim, todas as cartas precisam ser validadas. Quem assina as cartas: Analista AXA. Cópia nas tratativas internas (Reguladora e Cia): analistas: claudia.morgado@axa.com; ingrid.machado@axa.com. Cópia nas tratativas externas (Tomador, Corretor e Patrono): analistas: claudia.morgado@axa.com; ingrid.machado@axa.com. Concessão de prazos ao Segurado e Tomador: 15 dias corridos. Carta de Provisionamento: Sim. Ressarcimento: não
A5: Berkley | B5: Sim | C5: Sem orientação a respeito, seguir padrão da Addvalora | D5: Sim | E5: Acusação de recebimento e inicio imediato da abertura | F5: 5 dias para contato com a Cia após o recebimento do acionamento do sinistro. | G5: 5 dias para contato com a Cia após o recebimento do acionamento do sinistro. | H5: 5 dias contados da autorização para emissão do Relatório Final pela Cia. | I5: Sim | J5: Não aplicável | K5: Após 30 dias corridos da solicitação. | L5: 30 dias corridos após a 2ª reiteração. | M5: Não aplicável | N5: Não aplicável | O5: Não aplicável | P5: Não aplicável | Q5: Não aplicável | R5: Não aplicável | S5: Não aplicável | T5: Não aplicável | U5: Não | V5: Sem orientação a respeito | W5: Sem orientação a respeito | X5: Sim | Y5: Não | Z5: Layout dos Ofícios: Template Cia. Forma de envio de correspondências: E-mail e formato PDF. Requer aprovação da Cia.: Sim, todas as cartas precisam ser validadas. Quem assina as cartas: Analista Cia. Cópia nas tratativas internas (Reguladora e Cia): aferreira@berkley.com.br; ltureck@berkley.com.br; pquignoli@berkley.com.br Cópia nas tratativas externas (Tomador, Corretor e Patrono): aferreira@berkley.com.br; ltureck@berkley.com.br; pquignoli@berkley.com.br Concessão de prazos ao Segurado e Tomador: 15 dias corridos. Carta de Provisionamento: Sim. Ressarcimento: não.
A6: Daycoval | B6: Sim | C6: Sem orientação a respeito, seguir padrão da Addvalora | D6: Apenas nas tratativas internas (Seguradora e Addvalora). | E6: Acusação de recebimento e inicio imediato da abertura | F6: 5 dias (casos normais) e 3 dias (casos urgentes) para contato com a Cia após o recebimento do acionamento do sinistro. | G6: 5 dias (casos normais) e 3 dias (casos urgentes) para contato com a Cia após o recebimento do acionamento do sinistro. | H6: 3 dias contados da autorização para emissão do Relatório Final pela Cia. | I6: Sim | J6: Não aplicável | K6: Após 30 dias corridos da solicitação. | L6: 30 dias corridos após a 2ª reiteração. | M6: Não aplicável | N6: Não aplicável | O6: Não aplicável | P6: Não aplicável | Q6: Não aplicável | R6: Não aplicável | S6: Não aplicável | T6: Não aplicável | U6: Não | V6: Sem orientação a respeito | W6: Sem orientação a respeito | X6: Sim | Y6: Não | Z6: Layout dos Ofícios: Template Cia. Forma de envio de correspondências: E-mail (PDF). Envio físico em casos pontuais com prévia autorização da Cia. Requer aprovação da Cia.: Correspondências de impulso processual (sem cunho decisório): Em caso de apólices do setor público com IS igual ou superior a R$ 200.000,00 e para de apólices do setor privado com IS igual ou superior a R$ 100.000,00; - Correspondências de baixa sem ônus à BMG (verificar hipóteses no item 4.2.1 da SLA): Em casos com IS igual ou superior a R$ 200.000,00, independentemente do setor ou modalidade da Apólice. - Correspondências de negativa de indenização: todos os processos sob a condução da Addvalora, independentemente do ramo, complexidade e valor. - Correspondências com posicionamento final da Seguradora (RFS): todos os processos sob a condução da Addvalora, independentemente do ramo, complexidade e valor. Quem assina as cartas: Addvalora. Cópia nas tratativas internas (Reguladora e Cia): Analista BMG e Caixa de Backup documentos.sinistros@bmgseguros.com.br. Cópia nas tratativas externas (Tomador, Corretor e Patrono): Caixa de Backup documentos.sinistros@bmgseguros.com.br. Concessão de prazos ao Segurado e Tomador: Iniciais: 30 dias corridos Intermediárias: 15 dias corridos Carta de Provisionamento: Apenas em casos com sugestão de reserva acima de 50k. Abaixo desse valor, será apenas o Formulário (Check-list) no corpo do e-mail. Sempre informar em qual data ocorreu o fato gerador do sinistro (inadimplemento da multa aplicada – prazo final para pagamento espontâneo pelo Tomador ao Segurado). Ressarcimento: não.
A7: Essor | B7: Não | C7: Sem orientação a respeito, seguir padrão da Addvalora | D7: Apenas nas tratativas internas (Seguradora e Addvalora). | E7: Acusação de recebimento e inicio imediato da abertura | F7: 5 dias para contato com a Cia após o recebimento do acionamento do sinistro. | G7: 5 dias para contato com a Cia após o recebimento do acionamento do sinistro. | H7: 5 dias contados da autorização para emissão do Relatório Final pela Cia. | I7: Sim | J7: Não aplicável | K7: Após 30 dias corridos da solicitação. | L7: 30 dias corridos após a 2ª reiteração. | M7: Não aplicável | N7: Não aplicável | O7: Não aplicável | P7: Não aplicável | Q7: Não aplicável | R7: Não aplicável | S7: Não aplicável | T7: Não aplicável | U7: Não | V7: Sem orientação a respeito | W7: Sem orientação a respeito | X7: Sim | Y7: Não | Z7: Layout dos Ofícios: Template Cia. Forma de envio de correspondências: E-mail (PDF). O envio pelos correios ocorrerá apenas se não houver endereço eletrônico válido das partes, mediante prévia anuência da Seguradora. (em casos que o nosso limitador seja de até 10k, enviar no corpo do e-mail) Requer aprovação da Cia.: Apenas cartas estratégicas precisam ser validadas com o analista. Quem assina as cartas: Addvalora. Exceto: as cartas/RFR que encerramos o processo por negativa de pagamento de indenização devemos enviar à Seguradora para assinatura. Cópia nas tratativas internas (Reguladora e Cia): Analista Rayssa (rayssa.bercot@essor.com.br), com cópia para a Caixa departamental sinistro.garantia@essor.com.br. Cópia nas tratativas externas (Tomador, Corretor e Patrono): a Caixa departamental sinistro.garantia@essor.com.br. Concessão de prazos ao Segurado e Tomador: 15 dias corridos Carta de Provisionamento: As reservas devem seguir o seguinte critério: Remoto (R$ 1,00), Possível (35% do valor reclamado), Provável (100% do valor reclamado). No CPJ, nos casos que o provisionamento não seja 100%, devemos indicar o valor estimado conforme mencionado para a Cia, inserido no campo resultado a seguinte descrição: Exemplo: O valor da multa é de R$ 2.465,00, porém, conforme orientação da Seguradora, em se tratando de risco possível, indicamos a reserva de 35% do valor (R$ 862,75). Ressarcimento: Sim.
A8: Excelsior | B8: Sim | C8: Sim. Seguir padrão da Excelsior. | D8: Apenas nas tratativas internas (Seguradora e Addvalora). | E8: Acusação de recebimento e inicio imediato da abertura | F8: 5 dias para contato com a Cia após o recebimento do acionamento do sinistro. | G8: 5 dias para contato com a Cia após o recebimento do acionamento do sinistro. | H8: 5 dias contados da autorização para emissão do Relatório Final pela Cia. | I8: Sim | J8: Não aplicável | K8: Após 30 dias corridos da solicitação. | L8: 30 dias corridos após a 2ª reiteração. | M8: Não aplicável | N8: Não aplicável | O8: Não aplicável | P8: Não aplicável | Q8: Não aplicável | R8: Não aplicável | S8: Não aplicável | T8: Não aplicável | U8: Não | V8: Sem orientação a respeito | W8: Sem orientação a respeito | X8: Sim | Y8: Não | Z8: Layout dos Ofícios: Template Cia. Forma de envio de correspondências: E-mail (PDF) e Correios. (em casos que o nosso limitador seja de até 10k, enviar no corpo do e-mail) Requer aprovação da Cia.: Apenas cartas estratégicas precisam ser validadas com o analista. Quem assina as cartas: Addvalora. Exceto: carta de negativa e baixa e relatório finais precisam ser assinados pela Cia. Cópia nas tratativas internas (Reguladora e Cia): gabriella.abreu@excelsiorseguros.com.br; fernanda.brito@excelsiorseguros.com.br; at@excelsiorseguros.com.br e a Caixa Departamental regulacao@excelsiorseguros.com.br. Cópia nas tratativas externas (Tomador, Corretor e Patrono): a Caixa departamental regulacao@excelsiorseguros.com.br. Concessão de prazos ao Segurado e Tomador: 15 dias corridos Carta de Provisionamento: Sim. Ressarcimento: Sim.
A9: HDI | B9: Não | C9: Sem orientação a respeito, seguir padrão da Addvalora | D9: Sim | E9: Acusação de recebimento e inicio imediato da abertura | F9: 5 dias para contato com a Cia após o recebimento do acionamento do sinistro. | G9: 5 dias para contato com a Cia após o recebimento do acionamento do sinistro. | H9: 5 dias contados da autorização para emissão do Relatório Final pela Cia. | I9: Sim | J9: Não aplicável | K9: Após 30 dias corridos da solicitação. | L9: Pendente de alinhamento. | M9: Não aplicável | N9: Não aplicável | O9: Não aplicável | P9: Não aplicável | Q9: Não aplicável | R9: Não aplicável | S9: Não aplicável | T9: Não aplicável | U9: Não | V9: Sem orientação a respeito | W9: Sem orientação a respeito | X9: Sim | Y9: Não | Z9: Layout dos Ofícios: Template Addvalora. Apenas Relatório Final e notificação para pagamento espontâneo seguem com a logo da Cia. Forma de envio de correspondências: E-mail (PDF). Requer aprovação da Cia.: Todas as cartas. Quem assina as cartas: Addvalora. Cópia nas tratativas internas (Reguladora e Cia): luciano.inovellini@br.hdi.global e janaina.duarte@br.hdi.global. Cópia nas tratativas externas (Tomador, Corretor e Patrono): luciano.inovellini@br.hdi.global e janaina.duarte@br.hdi.global.
A10: Pottencial | B10: Não | C10: Sem orientação a respeito, seguir padrão da Addvalora | D10: Sim | E10: Acusação de recebimento e inicio imediato da abertura | F10: 5 dias para contato com a Cia após o recebimento do acionamento do sinistro. | G10: 5 dias para contato com a Cia após o recebimento do acionamento do sinistro. | H10: 5 dias contados da autorização para emissão do Relatório Final pela Cia. | I10: Sim | J10: Não aplicável | K10: Após 30 dias corridos da solicitação. Necessário validação da Cia. | L10: 30 dias corridos após a 1ª reiteração. | M10: Não aplicável | N10: Não aplicável | O10: Não aplicável | P10: Não aplicável | Q10: Não aplicável | R10: Não aplicável | S10: Não aplicável | T10: Não aplicável | U10: Não | V10: Sem orientação a respeito | W10: Sem orientação a respeito | X10: Sim | Y10: Não | Z10: Para e-mails de rotina e pedidos de documentos (apólice, CCG, informações comerciais etc.): flavia.marchiori@pottencial.com.br; sinistro.terminodeobra@pottencial.com.br Em fluxo de reuniões, copiar também: debora.nunes@pottencial.com.br
A11: Sombrero | B11: Sim | C11: Sim, padrão Addvalora e acréscimo número apólice. | D11: Apenas nas tratativas internas (Seguradora e Addvalora). | E11: Acusação de recebimento e inicio imediato da abertura | F11: 5 dias para contato com a Cia após o recebimento do acionamento do sinistro. | G11: 5 dias para contato com a Cia após o recebimento do acionamento do sinistro. | H11: 5 dias contados da autorização para emissão do Relatório Final pela Cia. | I11: Sim | J11: Não aplicável | K11: Após 30 dias corridos da solicitação. | L11: 30 dias corridos após a 2ª reiteração. | M11: Não aplicável | N11: Não aplicável | O11: Não aplicável | P11: Não aplicável | Q11: Não aplicável | R11: Não aplicável | S11: Não aplicável | T11: Não aplicável | U11: Não | V11: Sem orientação a respeito | W11: Sem orientação a respeito | X11: Sim | Y11: Não | Z11: Layout dos Ofícios: Template Cia Formato do envio das correspondências: E-mails. Envio físico em casos pontuais com autorização da Cia. Requer Aprovação da Cia.: Correspondências de baixa, de negativa de indenização ou com posicionamento final da Seguradora - RFS (que envolva questões de mérito), precisam ser validadas. Correspondências de impulso processual e de baixa sem ônus à Sombrero (sem cunho decisório), dispensam validação prévia. Quem copiar nas tratativas internas (Reguladora e Cia.): Quando for necessário aprovação de cartas/pareceres/relatórios: direcionar o email para Maria Monteiro (maria.monteiro@sombreroseguros.com.br) com cópia para Leticia Maso (leticia.maso@sombreroseguros.com.br); • Solicitação de CCG do Tomador: Idália Soares (idalia.soares@sombreroseguros.com.br) com cópia para Maria Monteiro (maria.monteiro@sombreroseguros.com.br); • Solicitação de convolação/pagamento do sinistro ou encerramento da expectativa: Idália Soares (idalia.soares@sombreroseguros.com.br) com cópia para Maria Monteiro (maria.monteiro@sombreroseguros.com.br), Leticia Maso (leticia.maso@sombreroseguros.com.br) e Daniel De Pauli (daniel.pauli@sombreroseguros.com.br); • Trocas de emails com os Segurados e Tomadores: Incluir apenas o e-mail do Sinistros Garantia (sinistros.garantia@sombreroseguros.com.br); • Atualizações sobre os processos: Sinistros Garantia (sinistros.garantia@sombreroseguros.com.br). Quem copiar nas tratativas externas (Tomador, Corretor, Patrono): sinistros.garantia@sombreroseguros.com.br Nos ofícios, colocar os seguintes e-mails para recebimento de intimação: sinistros.garantia@sombreroseguros.com.br Carta de Provisionamento: Apenas em casos com sugestão de reserva acima de 100k. Abaixo desse valor, pode ser no corpo do e-mail. Ressarcimento: Sim (necessita de autorização) Sistemas de Seguradoras: Sim – Gclaims
A12: Sompo | B12: Não | C12: Sem orientação a respeito, seguir padrão da Addvalora | D12: Sim | E12: Acusação de recebimento e inicio imediato da abertura | F12: 5 dias para contato com a Cia após o recebimento do acionamento do sinistro. | G12: 5 dias para contato com a Cia após o recebimento do acionamento do sinistro. | H12: 5 dias contados da autorização para emissão do Relatório Final pela Cia. | I12: Sim | J12: Não aplicável | K12: Após 30 dias corridos da solicitação. | L12: 30 dias corridos após a 2ª reiteração. | M12: Não aplicável | N12: Não aplicável | O12: Não aplicável | P12: Não aplicável | Q12: Não aplicável | R12: Não aplicável | S12: Não aplicável | T12: Não aplicável | U12: Não | V12: Sem orientação a respeito | W12: Sem orientação a respeito | X12: Sim | Y12: Não | Z12: Layout dos Ofícios Template Cia Requer aprovação da Cia. Não. Exceto cartas de baixas, negativas, posicionamento de cobertura, devem ser validadas pela Cia. Quem copiar nas tratativas internas (Reguladora e Cia.) flspio@sompo.com.br, epsantos@sompo.com.br e sinistrocorporativo@sompo.com.br Quem copiar nas tratativas externas (Tomador, Corretor, Patrono) flspio@sompo.com.br, sinistrocorporativo@sompo.com.br Ressarcimento Não Sistemas de Seguradoras Não

Sheet Garantia - ECTO
A1: Seguradora | B1: Sistema | C1: Trocar campo de assunto do e-mail | D1: Copiar o analista em todos os e-mails | E1: SLA - 1º Contato e agendamento vistoria | F1: SLA- Realização da vistoria / Síntese | G1: SLA - Relatório Preliminar | H1: SLA - Relatório Final | I1: Relatório de regulação modelo próprio | J1: Cronologia no relatório (sugestão utilizar em todos os processos) | K1: Períodos para reiterações de documentos (SLA) | L1: Prazo de encerramento sem manifestação / documentos- (Cycle Time) | M1: Depreciação | N1: Valor em Risco | O1: Salvados | Q1: Apresentação da apuração ao segurado antes da seguradora analisar os valores | R1: Emissão termo de acordo / demonstrativo de prejuízos | U1: Precisa enviar relatório final junto com time sheet / despesas | V1: Envio do relatório final junto com a nota fiscal | W1: Formulários Próprios | X1: Emissão carta de encerramento / Negativa | Z1: Outros procedimentos e assuntos
M2: Reter a D.V.N | O2: Área de Salvados | P2: Sistema | R2: Regulação | S2: Seguradora | T2: Modelo próprio | X2: Regulação | Y2: Seguradora
A3: Pottencial | B3: Não | C3: Inclusão do nome do empreendimento, e após seguir com o padrão Addvalora | D3: Sim | E3: Acusação de recebimento e inicio imediato da abertura | F3: Vistoria ocorrerá após análise da expectativa de sinistro, observados o envio das 3 (três) notificações pela CEF, e não identificado qualquer perda de direitos | G3: 5 dias após o recebimento da expectativa de sinistro/sinistro pela Reguladora | H3: Após a realização da vistoria | I3: Sim | J3: Sim | K3: 15 dias | L3: Apenas ao Segurado, 30 dias corridos após a 1ª reiteração. | M3: Não aplicável | N3: Não aplicável | O3: Não aplicável | P3: Não aplicável | Q3: Não aplicável | R3: Não aplicável | S3: Não aplicável | T3: Não aplicável | U3: Não | V3: Não | W3: Não | X3: Sim | Y3: Não | Z3: Para e-mails de rotina e pedidos de documentos (apólice, CCG, informações comerciais etc.): flavia.marchiori@pottencial.com.br; sinistro.terminodeobra@pottencial.com.br Em fluxo de reuniões, copiar também: debora.nunes@pottencial.com.br
A4: Sombrero | B4: Sim | C4: Sem orientação a respeito, seguir padrão da Addvalora | D4: Sim | E4: Acusação de recebimento e inicio imediato da abertura | F4: Vistoria ocorrerá após análise da expectativa de sinistro, observados o envio das 3 (três) notificações pela CEF, e não identificado qualquer perda de direitos | G4: 5 dias após o recebimento da expectativa de sinistro/sinistro pela Reguladora | H4: Após a confecção da orçamentação | I4: Sim | J4: Sim | K4: 15 dias | L4: Apenas ao Segurado, 30 dias corridos após a 1ª reiteração. | M4: Não aplicável | N4: Não aplicável | O4: Não aplicável | P4: Não aplicável | Q4: Não aplicável | R4: Não aplicável | S4: Não aplicável | T4: Não aplicável | U4: Não | V4: Não | W4: Não | X4: Sim | Y4: Não | Z4: Layout dos Ofícios: Template Cia Requer Aprovação da Cia.: Sim (teses novas) Quem copiar nas tratativas internas (Reguladora e Cia.): Para e-mails de rotina e pedidos de documentos (apólice, CCG, informações comerciais etc.): sinistros.garantia@sombreroseguros.com.br Para e-mails de tomada de decisão: daniel.pauli@sombreroseguros.com.br, leticia.maso@sombreroseguros.com.br, maria.monteiro@sombreroseguros.com.br, sinistros.garantia@sombreroseguros.com.br e barbara.nascimento@sombreroseguros.com.br Quem copiar nas tratativas externas (Tomador, Corretor, Patrono): sinistros.garantia@sombreroseguros.com.br Nos ofícios, colocar os seguintes e-mails para recebimento de intimação: sinistros.garantia@sombreroseguros.com.br e garantiajudicial@addvaloraglobal.com Carta de Provisionamento: Indenizações acima de 100k Prazo de Envio do Provisionamento: D-3 Ressarcimento: Sim (necessita de autorização) Sistemas de Seguradoras: Sim – Gclaims

Sheet Boticário
A1: Seguradora | B1: Sistema | C1: Trocar campo de assunto do e-mail | D1: Copiar o analista em todos os e-mails | E1: SLA - 1º Contato e agendamento vistoria | F1: SLA- Realização da vistoria / Síntese | G1: SLA - Relatório Preliminar | H1: SLA - Relatório Final | I1: Relatório de regulação modelo próprio | J1: Cronologia no relatório (sugestão utilizar em todos os processos) | K1: Períodos para reiterações de documentos (SLA) | L1: Prazo de encerramento sem manifestação / documentos- (Cycle Time) | M1: Depreciação | N1: Valor em Risco | O1: Salvados | Q1: Apresentação da apuração ao segurado antes da seguradora analisar os valores | R1: Emissão termo de acordo / demonstrativo de prejuízos | U1: Precisa enviar relatório final junto com time sheet / despesas | V1: Envio do relatório final junto com a nota fiscal | W1: Formulários Próprios | X1: Emissão carta de encerramento / Negativa | Z1: Outros procedimentos e assuntos
M2: Reter a D.V.N | O2: Área de Salvados | P2: Sistema | R2: Regulação | S2: Seguradora | T2: Modelo próprio | X2: Regulação | Y2: Seguradora
A3: BMG / Daycoval | B3: Sim. Mas para o Boticário não se uiliza pois o sistema da Daycoval passará por mudanças | C3: Sem orientação a respeito. Seguir padrão da Addvalora | D3: Sim e também a caixa departamental | E3: Orientação : Manter contato imediato após o recebimento do acionamento | F3: Conforme agendamento / apresentar a sintese até 48h após a vistoria e não colher assinatua do segurado no momento da vistoria | G3: Até 5 dias após a vistoria | H3: Até 5 dias úteis após último documento (Vide observações na coluna outros assuntos) | I3: Sem informação | J3: Sim | K3: A cada 15 dias. Obs. Tem lista predefinida de documentos para alguns tipos de sinistros (vide documento denominado "Protocolo de sinistro") | L3: Completados 2 meses ( 60 dias ) da solicitação de documentos, a Seguradora encaminhará ao Franquea-do/Segurado a notificação de encerramento, com o encerramento formalizado à área de Seguros em ( 90 dias ), com o envio da Carta de Encerramento ao final do prazo de ( 120 dias ). | M3: Conforme apólice (tem particularidades e cláusula de valor de novo) 7ª Cláusula Particular - Critério de Indenização a. Padronização de Loja (Maquinismos, Moveis, Utensílios): Valor de Nova, limitada a 02 (duas) vezes ao Valor Atual; b. Padronização de Loja Descontinuada (Maquinismos, Moveis, Utensílios): Valor de Novo da padronização mais recente, limitada a 02 (duas) vezes o valor da padronização descontinuada; c. Edificações e Instalações: Custos de reconstrução do imóvel, incluindo instalações como piso, iluminação e benfeitorias, ainda que o imóvel pertença a terceiros. c. d. Mercadorias: d. Conforme valor de nota fiscal de aquisição, acrescido de TRF(taxa de remuneração de Franquia) até 45% (quarenta e cinco por cento) do valor total de suas compras de produtos O Boticário, quem disse, Berenice?, O.U.I. – Original Unique Individuel, e até 65% (sessenta e cinco por cento) do valor total de suas compras de produtos Eudora (sell in) e REM (Recuperação de Esforço de Marketing) até 15%, sempre limitado ao VRD (Valor em Risco Declarado) de cada local; e e. eventuais impostos comprovados conforme política fiscal adotada pelo Segurado, não limitados ao VRD de cada local. f. Infraestrutura de TI da loja: Será considerado o Valor de Novo Total do Kit danificado – Neste item de valor de novo entram também os celulares. Portanto não se aplica depreciação | N3: E-mail para analista para ver se levanta o VR para prejuízos de até 5% do Valor em Risco Declarado ou atuar conforme particularidades da apólice Obs. Tem apólice que até determinado valor não apura o VR | O3: Sem informação / E-mail para o analista | P3: Não | Q3: Sim . Primeiro apresenta a planilha de apuração ao segurado e estando de acordo, envio do relatório para a seguradora, que por sua vez fará a análise e autorizará e elaboração do termo de pagamento | R3: Sim | S3: Não | T3: Sim | U3: Sem orientação a respeito | V3: Sem orientação a respeito | W3: Sim | X3: Sim. Elaboramos a carta e enviamos para análise da seguradora | Y3: Não | Z3: *Caixa departamental: documentos.sinistros@bmgseguros.com.br *Tem modelo Termo de Pagamento e Demonstrativo de Prejuízos *O contato direto com o segurado é somente para agendamento da vistoria, posteriormente todos dos demais contatos serão via corretor *Aplicação TRF ( Franchising) - O percentual varia para cada tipo de risco, desta forma, o corretor sempre fornecerá o percentual correto a ser aplicado para cada caso. A TRF aplicasse sobre os valores das mercadorias reclamadas e está acordado na apólice. *Na vistoria colher as informações presentes na" ficha de risco" e posteriormente enviar a ficha preenchida juntamente com o relatório preliminar. *Tem modelo de planilha de apuração ( Pendências em amarelo e laranja – Estas cores representam a legenda de pendências acordadas com o corretor, que quando identificadas, devemos apontar na planilha de apuração) . Não pode haver alteração das cores e no modelo da planilha *Quando recebermos os documentos e logo já identificarmos pendências e estas pendências não permitam avançar com a apuração, sugiro que a resposta tenha que ocorrer o mais breve possível ao corretor indicando as referidas pendências. No caso de recebermos documentos parciais e também identificado pendências, devolvemos a pendência ao corretor e indicamos que os demais documentos serão analisados. * Sempre que já tivermos documentos parciais e ou totais, referente a apuração, devemos enviar a planilha ao corretor com a apuraçãol. Nos casos que não recebemos documentos que permitam a apuração ou estejam divergentes, apontar na planilha estas pendências e ou divergências. Em resumo, a planilha tem que ser enviada, seja para apuração parcial ou final. Após o segurado concordar com o valor da planilha de apuração, devemos enviar o relatório final para análise da seguradora e por sua vez irá analisar e sinalizar se podemos enviar o termo de pagemento e o demonstrativo ao segurado para assinatura Sinistros até R$ 30.000,00 de Prejuízos: Quando do recebimento dos documentos, a reguladora terá até 5 úteis dias para analisar tais documen-tos e se for o caso reiterar a solicitação dos documentos que não foram encaminhados. Se os documentos estiverem completos a reguladora encaminhará o demonstrativo dos prejuízos para análise e de acordo do Segurado, juntamente com o termo de quitação para preenchimento (dentro dos 5 dias úteis). Após o recebimento do “de acordo” e do termo de quitação contendo os dados bancários, a Seguradora tem 10 dias corridos para realizar o pagamento da indenização. Sinistros Superiores a R$ 30.000,00 de Prejuízos: Num primeiro momento, devem ser seguidos os prazos estipulados para os casos até (R$ 30.000,00). Po-rém, a depender da complexidade da ocorrência, os prazos serão revisados caso a caso. Existe um documento denominado Protocolo de Sinistro, onde constam todas as particularidades das tratativas dos processos Boticário ( procurar o coordenador para obter a cópia do documento)
